[
  {
    "Sep": "Sep",
    "Total": "Total",
    "Dec": "Dec",
    "May": "May",
    "Apr": "Apr",
    "Nov": "Nov",
    "City": "City",
    "Oct": "Oct",
    "Jun": "Jun",
    "Aug": "Aug",
    "Mar": "Mar",
    "Feb": "Feb",
    "Jan": "Jan",
    "Jul": "Jul"
  },
  {
    "Sep": "",
    "Total": "1",
    "Dec": "",
    "May": "",
    "Apr": "",
    "Nov": "",
    "City": "Afton",
    "Oct": "",
    "Jun": "",
    "Aug": "",
    "Mar": "",
    "Feb": "",
    "Jan": "",
    "Jul": "1"
  },
  {
    "Sep": "",
    "Total": "2",
    "Dec": "",
    "May": "",
    "Apr": "",
    "Nov": "",
    "City": "Aitkin",
    "Oct": "",
    "Jun": "",
    "Aug": "2",
    "Mar": "",
    "Feb": "",
    "Jan": "",
    "Jul": ""
  },
  {
    "Sep": "",
    "Total": "2",
    "Dec": "",
    "May": "1",
    "Apr": "",
    "Nov": "",
    "City": "Albert Lea",
    "Oct": "",
    "Jun": "",
    "Aug": "",
    "Mar": "",
    "Feb": "",
    "Jan": "",
    "Jul": "1"
  },
  {
    "Sep": "3",
    "Total": "11",
    "Dec": "",
    "May": "3",
    "Apr": "",
    "Nov": "",
    "City": "Alexandria",
    "Oct": "1",
    "Jun": "2",
    "Aug": "1",
    "Mar": "",
    "Feb": "",
    "Jan": "",
    "Jul": "1"
  },
  {
    "Sep": "",
    "Total": "1",
    "Dec": "",
    "May": "",
    "Apr": "",
    "Nov": "",
    "City": "Almelund",
    "Oct": "1",
    "Jun": "",
    "Aug": "",
    "Mar": "",
    "Feb": "",
    "Jan": "",
    "Jul": ""
  },
  {
    "Sep": "2",
    "Total": "17",
    "Dec": "",
    "May": "4",
    "Apr": "2",
    "Nov": "1",
    "City": "Andover",
    "Oct": "",
    "Jun": "2",
    "Aug": "2",
    "Mar": "1",
    "Feb": "",
    "Jan": "",
    "Jul": "3"
  },
  {
    "Sep": "",
    "Total": "2",
    "Dec": "",
    "May": "",
    "Apr": "",
    "Nov": "",
    "City": "Annandale",
    "Oct": "",
    "Jun": "",
    "Aug": "",
    "Mar": "",
    "Feb": "",
    "Jan": "",
    "Jul": "2"
  },
  {
    "Sep": "",
    "Total": "3",
    "Dec": "",
    "May": "1",
    "Apr": "1",
    "Nov": "",
    "City": "Anoka",
    "Oct": "1",
    "Jun": "",
    "Aug": "",
    "Mar": "",
    "Feb": "",
    "Jan": "",
    "Jul": ""
  },
  {
    "Sep": "",
    "Total": "5",
    "Dec": "1",
    "May": "1",
    "Apr": "",
    "Nov": "",
    "City": "Apple Valley",
    "Oct": "",
    "Jun": "",
    "Aug": "1",
    "Mar": "",
    "Feb": "",
    "Jan": "",
    "Jul": "2"
  },
  {
    "Sep": "",
    "Total": "1",
    "Dec": "",
    "May": "",
    "Apr": "",
    "Nov": "",
    "City": "Arden Hills",
    "Oct": "",
    "Jun": "",
    "Aug": "",
    "Mar": "1",
    "Feb": "",
    "Jan": "",
    "Jul": ""
  },
  {
    "Sep": "1",
    "Total": "1",
    "Dec": "",
    "May": "",
    "Apr": "",
    "Nov": "",
    "City": "Argyle",
    "Oct": "",
    "Jun": "",
    "Aug": "",
    "Mar": "",
    "Feb": "",
    "Jan": "",
    "Jul": ""
  },
  {
    "Sep": "1",
    "Total": "1",
    "Dec": "",
    "May": "",
    "Apr": "",
    "Nov": "",
    "City": "Arlington",
    "Oct": "",
    "Jun": "",
    "Aug": "",
    "Mar": "",
    "Feb": "",
    "Jan": "",
    "Jul": ""
  },
  {
    "Sep": "",
    "Total": "1",
    "Dec": "",
    "May": "",
    "Apr": "",
    "Nov": "",
    "City": "Ashby",
    "Oct": "",
    "Jun": "",
    "Aug": "",
    "Mar": "",
    "Feb": "",
    "Jan": "",
    "Jul": "1"
  },
  {
    "Sep": "",
    "Total": "1",
    "Dec": "",
    "May": "",
    "Apr": "",
    "Nov": "",
    "City": "Audubon",
    "Oct": "",
    "Jun": "1",
    "Aug": "",
    "Mar": "",
    "Feb": "",
    "Jan": "",
    "Jul": ""
  },
  {
    "Sep": "3",
    "Total": "7",
    "Dec": "",
    "May": "1",
    "Apr": "",
    "Nov": "",
    "City": "Austin",
    "Oct": "",
    "Jun": "1",
    "Aug": "",
    "Mar": "",
    "Feb": "1",
    "Jan": "",
    "Jul": "1"
  },
  {
    "Sep": "",
    "Total": "1",
    "Dec": "",
    "May": "",
    "Apr": "",
    "Nov": "",
    "City": "Barnesville",
    "Oct": "",
    "Jun": "",
    "Aug": "1",
    "Mar": "",
    "Feb": "",
    "Jan": "",
    "Jul": ""
  },
  {
    "Sep": "",
    "Total": "2",
    "Dec": "",
    "May": "",
    "Apr": "",
    "Nov": "",
    "City": "Battle Lake",
    "Oct": "",
    "Jun": "",
    "Aug": "",
    "Mar": "",
    "Feb": "",
    "Jan": "",
    "Jul": "2"
  },
  {
    "Sep": "",
    "Total": "2",
    "Dec": "",
    "May": "",
    "Apr": "",
    "Nov": "",
    "City": "Baudette",
    "Oct": "",
    "Jun": "1",
    "Aug": "",
    "Mar": "",
    "Feb": "",
    "Jan": "",
    "Jul": "1"
  },
  {
    "Sep": "",
    "Total": "5",
    "Dec": "",
    "May": "",
    "Apr": "",
    "Nov": "1",
    "City": "Baxter",
    "Oct": "",
    "Jun": "1",
    "Aug": "3",
    "Mar": "",
    "Feb": "",
    "Jan": "",
    "Jul": ""
  },
  {
    "Sep": "",
    "Total": "1",
    "Dec": "",
    "May": "",
    "Apr": "",
    "Nov": "",
    "City": "Bayport",
    "Oct": "",
    "Jun": "",
    "Aug": "",
    "Mar": "",
    "Feb": "",
    "Jan": "",
    "Jul": "1"
  },
  {
    "Sep": "",
    "Total": "6",
    "Dec": "",
    "May": "1",
    "Apr": "",
    "Nov": "",
    "City": "Becker",
    "Oct": "1",
    "Jun": "2",
    "Aug": "1",
    "Mar": "1",
    "Feb": "",
    "Jan": "",
    "Jul": ""
  },
  {
    "Sep": "",
    "Total": "1",
    "Dec": "",
    "May": "",
    "Apr": "",
    "Nov": "",
    "City": "Bejou",
    "Oct": "",
    "Jun": "1",
    "Aug": "",
    "Mar": "",
    "Feb": "",
    "Jan": "",
    "Jul": ""
  },
  {
    "Sep": "",
    "Total": "3",
    "Dec": "",
    "May": "",
    "Apr": "",
    "Nov": "",
    "City": "Belle Plaine",
    "Oct": "1",
    "Jun": "",
    "Aug": "1",
    "Mar": "",
    "Feb": "",
    "Jan": "",
    "Jul": "1"
  },
  {
    "Sep": "1",
    "Total": "9",
    "Dec": "",
    "May": "",
    "Apr": "1",
    "Nov": "",
    "City": "Bemidji",
    "Oct": "2",
    "Jun": "",
    "Aug": "1",
    "Mar": "1",
    "Feb": "",
    "Jan": "1",
    "Jul": "2"
  },
  {
    "Sep": "",
    "Total": "1",
    "Dec": "",
    "May": "",
    "Apr": "",
    "Nov": "",
    "City": "Bertha",
    "Oct": "",
    "Jun": "",
    "Aug": "",
    "Mar": "",
    "Feb": "",
    "Jan": "",
    "Jul": "1"
  },
  {
    "Sep": "",
    "Total": "5",
    "Dec": "",
    "May": "",
    "Apr": "",
    "Nov": "",
    "City": "Big Lake",
    "Oct": "1",
    "Jun": "1",
    "Aug": "2",
    "Mar": "",
    "Feb": "",
    "Jan": "",
    "Jul": "1"
  },
  {
    "Sep": "1",
    "Total": "1",
    "Dec": "",
    "May": "",
    "Apr": "",
    "Nov": "",
    "City": "Bigfork",
    "Oct": "",
    "Jun": "",
    "Aug": "",
    "Mar": "",
    "Feb": "",
    "Jan": "",
    "Jul": ""
  },
  {
    "Sep": "",
    "Total": "1",
    "Dec": "",
    "May": "",
    "Apr": "",
    "Nov": "",
    "City": "Bird Island",
    "Oct": "",
    "Jun": "1",
    "Aug": "",
    "Mar": "",
    "Feb": "",
    "Jan": "",
    "Jul": ""
  },
  {
    "Sep": "",
    "Total": "2",
    "Dec": "",
    "May": "",
    "Apr": "",
    "Nov": "",
    "City": "Biwabik",
    "Oct": "",
    "Jun": "",
    "Aug": "1",
    "Mar": "",
    "Feb": "",
    "Jan": "",
    "Jul": "1"
  },
  {
    "Sep": "2",
    "Total": "6",
    "Dec": "",
    "May": "",
    "Apr": "",
    "Nov": "1",
    "City": "Blaine",
    "Oct": "3",
    "Jun": "",
    "Aug": "",
    "Mar": "",
    "Feb": "",
    "Jan": "",
    "Jul": ""
  },
  {
    "Sep": "4",
    "Total": "28",
    "Dec": "3",
    "May": "3",
    "Apr": "",
    "Nov": "",
    "City": "Bloomington",
    "Oct": "5",
    "Jun": "2",
    "Aug": "4",
    "Mar": "",
    "Feb": "2",
    "Jan": "4",
    "Jul": "1"
  },
  {
    "Sep": "",
    "Total": "1",
    "Dec": "",
    "May": "",
    "Apr": "",
    "Nov": "",
    "City": "Braham",
    "Oct": "",
    "Jun": "",
    "Aug": "1",
    "Mar": "",
    "Feb": "",
    "Jan": "",
    "Jul": ""
  },
  {
    "Sep": "",
    "Total": "3",
    "Dec": "",
    "May": "",
    "Apr": "",
    "Nov": "",
    "City": "Brainerd",
    "Oct": "1",
    "Jun": "2",
    "Aug": "",
    "Mar": "",
    "Feb": "",
    "Jan": "",
    "Jul": ""
  },
  {
    "Sep": "",
    "Total": "1",
    "Dec": "",
    "May": "1",
    "Apr": "",
    "Nov": "",
    "City": "Brooklyn Center",
    "Oct": "",
    "Jun": "",
    "Aug": "",
    "Mar": "",
    "Feb": "",
    "Jan": "",
    "Jul": ""
  },
  {
    "Sep": "",
    "Total": "3",
    "Dec": "",
    "May": "",
    "Apr": "",
    "Nov": "",
    "City": "Brooklyn Park",
    "Oct": "",
    "Jun": "2",
    "Aug": "1",
    "Mar": "",
    "Feb": "",
    "Jan": "",
    "Jul": ""
  },
  {
    "Sep": "1",
    "Total": "5",
    "Dec": "",
    "May": "1",
    "Apr": "",
    "Nov": "",
    "City": "Buffalo",
    "Oct": "",
    "Jun": "2",
    "Aug": "1",
    "Mar": "",
    "Feb": "",
    "Jan": "",
    "Jul": ""
  },
  {
    "Sep": "",
    "Total": "1",
    "Dec": "",
    "May": "",
    "Apr": "",
    "Nov": "",
    "City": "Buffalo Lake",
    "Oct": "",
    "Jun": "",
    "Aug": "",
    "Mar": "",
    "Feb": "1",
    "Jan": "",
    "Jul": ""
  },
  {
    "Sep": "1",
    "Total": "4",
    "Dec": "",
    "May": "1",
    "Apr": "",
    "Nov": "1",
    "City": "Burnsville",
    "Oct": "",
    "Jun": "1",
    "Aug": "",
    "Mar": "",
    "Feb": "",
    "Jan": "",
    "Jul": ""
  },
  {
    "Sep": "",
    "Total": "1",
    "Dec": "",
    "May": "",
    "Apr": "",
    "Nov": "",
    "City": "Butterfield",
    "Oct": "",
    "Jun": "",
    "Aug": "",
    "Mar": "",
    "Feb": "",
    "Jan": "",
    "Jul": "1"
  },
  {
    "Sep": "",
    "Total": "1",
    "Dec": "",
    "May": "",
    "Apr": "",
    "Nov": "",
    "City": "Byron",
    "Oct": "",
    "Jun": "",
    "Aug": "",
    "Mar": "",
    "Feb": "",
    "Jan": "",
    "Jul": "1"
  },
  {
    "Sep": "",
    "Total": "3",
    "Dec": "",
    "May": "",
    "Apr": "",
    "Nov": "",
    "City": "Caledonia",
    "Oct": "1",
    "Jun": "1",
    "Aug": "1",
    "Mar": "",
    "Feb": "",
    "Jan": "",
    "Jul": ""
  },
  {
    "Sep": "1",
    "Total": "4",
    "Dec": "",
    "May": "2",
    "Apr": "1",
    "Nov": "",
    "City": "Cambridge",
    "Oct": "",
    "Jun": "",
    "Aug": "",
    "Mar": "",
    "Feb": "",
    "Jan": "",
    "Jul": ""
  },
  {
    "Sep": "1",
    "Total": "2",
    "Dec": "",
    "May": "",
    "Apr": "",
    "Nov": "",
    "City": "Canby",
    "Oct": "",
    "Jun": "1",
    "Aug": "",
    "Mar": "",
    "Feb": "",
    "Jan": "",
    "Jul": ""
  },
  {
    "Sep": "",
    "Total": "1",
    "Dec": "",
    "May": "",
    "Apr": "1",
    "Nov": "",
    "City": "Cannon Falls",
    "Oct": "",
    "Jun": "",
    "Aug": "",
    "Mar": "",
    "Feb": "",
    "Jan": "",
    "Jul": ""
  },
  {
    "Sep": "",
    "Total": "1",
    "Dec": "",
    "May": "",
    "Apr": "",
    "Nov": "",
    "City": "Carlton",
    "Oct": "",
    "Jun": "",
    "Aug": "",
    "Mar": "",
    "Feb": "",
    "Jan": "",
    "Jul": "1"
  },
  {
    "Sep": "2",
    "Total": "2",
    "Dec": "",
    "May": "",
    "Apr": "",
    "Nov": "",
    "City": "Carver",
    "Oct": "",
    "Jun": "",
    "Aug": "",
    "Mar": "",
    "Feb": "",
    "Jan": "",
    "Jul": ""
  },
  {
    "Sep": "",
    "Total": "1",
    "Dec": "",
    "May": "",
    "Apr": "",
    "Nov": "",
    "City": "Cass Lake",
    "Oct": "",
    "Jun": "1",
    "Aug": "",
    "Mar": "",
    "Feb": "",
    "Jan": "",
    "Jul": ""
  },
  {
    "Sep": "",
    "Total": "1",
    "Dec": "",
    "May": "",
    "Apr": "",
    "Nov": "",
    "City": "Center City",
    "Oct": "",
    "Jun": "",
    "Aug": "",
    "Mar": "",
    "Feb": "",
    "Jan": "1",
    "Jul": ""
  },
  {
    "Sep": "2",
    "Total": "4",
    "Dec": "",
    "May": "",
    "Apr": "",
    "Nov": "",
    "City": "Centerville",
    "Oct": "",
    "Jun": "",
    "Aug": "",
    "Mar": "1",
    "Feb": "",
    "Jan": "",
    "Jul": "1"
  },
  {
    "Sep": "",
    "Total": "1",
    "Dec": "",
    "May": "",
    "Apr": "",
    "Nov": "",
    "City": "Champlin",
    "Oct": "",
    "Jun": "",
    "Aug": "",
    "Mar": "",
    "Feb": "1",
    "Jan": "",
    "Jul": ""
  },
  {
    "Sep": "1",
    "Total": "5",
    "Dec": "",
    "May": "",
    "Apr": "",
    "Nov": "",
    "City": "Chanhassen",
    "Oct": "",
    "Jun": "1",
    "Aug": "",
    "Mar": "",
    "Feb": "",
    "Jan": "2",
    "Jul": "1"
  },
  {
    "Sep": "",
    "Total": "7",
    "Dec": "",
    "May": "3",
    "Apr": "",
    "Nov": "1",
    "City": "Chaska",
    "Oct": "",
    "Jun": "2",
    "Aug": "1",
    "Mar": "",
    "Feb": "",
    "Jan": "",
    "Jul": ""
  },
  {
    "Sep": "",
    "Total": "1",
    "Dec": "",
    "May": "",
    "Apr": "",
    "Nov": "",
    "City": "Chatfield",
    "Oct": "",
    "Jun": "1",
    "Aug": "",
    "Mar": "",
    "Feb": "",
    "Jan": "",
    "Jul": ""
  },
  {
    "Sep": "",
    "Total": "1",
    "Dec": "",
    "May": "",
    "Apr": "",
    "Nov": "",
    "City": "Chisago City",
    "Oct": "",
    "Jun": "",
    "Aug": "1",
    "Mar": "",
    "Feb": "",
    "Jan": "",
    "Jul": ""
  },
  {
    "Sep": "",
    "Total": "3",
    "Dec": "",
    "May": "",
    "Apr": "",
    "Nov": "1",
    "City": "Chisago Lakes",
    "Oct": "",
    "Jun": "",
    "Aug": "",
    "Mar": "",
    "Feb": "",
    "Jan": "",
    "Jul": "2"
  },
  {
    "Sep": "",
    "Total": "1",
    "Dec": "",
    "May": "",
    "Apr": "",
    "Nov": "",
    "City": "Chisholm",
    "Oct": "",
    "Jun": "",
    "Aug": "1",
    "Mar": "",
    "Feb": "",
    "Jan": "",
    "Jul": ""
  },
  {
    "Sep": "",
    "Total": "1",
    "Dec": "",
    "May": "",
    "Apr": "",
    "Nov": "",
    "City": "Circle Pines",
    "Oct": "",
    "Jun": "",
    "Aug": "",
    "Mar": "",
    "Feb": "",
    "Jan": "1",
    "Jul": ""
  },
  {
    "Sep": "",
    "Total": "3",
    "Dec": "",
    "May": "",
    "Apr": "",
    "Nov": "",
    "City": "Clearwater",
    "Oct": "",
    "Jun": "1",
    "Aug": "1",
    "Mar": "",
    "Feb": "",
    "Jan": "",
    "Jul": "1"
  },
  {
    "Sep": "3",
    "Total": "8",
    "Dec": "",
    "May": "2",
    "Apr": "",
    "Nov": "",
    "City": "Cloquet",
    "Oct": "2",
    "Jun": "",
    "Aug": "",
    "Mar": "",
    "Feb": "",
    "Jan": "",
    "Jul": "1"
  },
  {
    "Sep": "",
    "Total": "1",
    "Dec": "",
    "May": "1",
    "Apr": "",
    "Nov": "",
    "City": "Cohasset",
    "Oct": "",
    "Jun": "",
    "Aug": "",
    "Mar": "",
    "Feb": "",
    "Jan": "",
    "Jul": ""
  },
  {
    "Sep": "",
    "Total": "1",
    "Dec": "",
    "May": "",
    "Apr": "",
    "Nov": "",
    "City": "Cokato",
    "Oct": "",
    "Jun": "1",
    "Aug": "",
    "Mar": "",
    "Feb": "",
    "Jan": "",
    "Jul": ""
  },
  {
    "Sep": "",
    "Total": "5",
    "Dec": "",
    "May": "1",
    "Apr": "1",
    "Nov": "",
    "City": "Cold Spring",
    "Oct": "",
    "Jun": "1",
    "Aug": "1",
    "Mar": "",
    "Feb": "",
    "Jan": "",
    "Jul": "1"
  },
  {
    "Sep": "",
    "Total": "1",
    "Dec": "",
    "May": "",
    "Apr": "",
    "Nov": "",
    "City": "Collegeville",
    "Oct": "1",
    "Jun": "",
    "Aug": "",
    "Mar": "",
    "Feb": "",
    "Jan": "",
    "Jul": ""
  },
  {
    "Sep": "1",
    "Total": "4",
    "Dec": "",
    "May": "1",
    "Apr": "",
    "Nov": "",
    "City": "Coon Rapids",
    "Oct": "",
    "Jun": "",
    "Aug": "",
    "Mar": "",
    "Feb": "",
    "Jan": "2",
    "Jul": ""
  },
  {
    "Sep": "",
    "Total": "1",
    "Dec": "",
    "May": "",
    "Apr": "",
    "Nov": "",
    "City": "Corcoran",
    "Oct": "",
    "Jun": "",
    "Aug": "1",
    "Mar": "",
    "Feb": "",
    "Jan": "",
    "Jul": ""
  },
  {
    "Sep": "",
    "Total": "4",
    "Dec": "",
    "May": "1",
    "Apr": "",
    "Nov": "1",
    "City": "Cottage Grove",
    "Oct": "",
    "Jun": "1",
    "Aug": "",
    "Mar": "",
    "Feb": "",
    "Jan": "",
    "Jul": "1"
  },
  {
    "Sep": "",
    "Total": "1",
    "Dec": "",
    "May": "",
    "Apr": "",
    "Nov": "",
    "City": "Cottonwood",
    "Oct": "",
    "Jun": "",
    "Aug": "",
    "Mar": "",
    "Feb": "",
    "Jan": "",
    "Jul": "1"
  },
  {
    "Sep": "",
    "Total": "2",
    "Dec": "",
    "May": "",
    "Apr": "1",
    "Nov": "",
    "City": "Crookston",
    "Oct": "",
    "Jun": "",
    "Aug": "1",
    "Mar": "",
    "Feb": "",
    "Jan": "",
    "Jul": ""
  },
  {
    "Sep": "",
    "Total": "3",
    "Dec": "",
    "May": "",
    "Apr": "",
    "Nov": "",
    "City": "Crosslake",
    "Oct": "1",
    "Jun": "",
    "Aug": "",
    "Mar": "1",
    "Feb": "",
    "Jan": "",
    "Jul": "1"
  },
  {
    "Sep": "",
    "Total": "1",
    "Dec": "",
    "May": "",
    "Apr": "1",
    "Nov": "",
    "City": "Crosstown",
    "Oct": "",
    "Jun": "",
    "Aug": "",
    "Mar": "",
    "Feb": "",
    "Jan": "",
    "Jul": ""
  },
  {
    "Sep": "1",
    "Total": "2",
    "Dec": "",
    "May": "",
    "Apr": "",
    "Nov": "",
    "City": "Crystal",
    "Oct": "",
    "Jun": "",
    "Aug": "",
    "Mar": "",
    "Feb": "",
    "Jan": "",
    "Jul": "1"
  },
  {
    "Sep": "",
    "Total": "1",
    "Dec": "",
    "May": "",
    "Apr": "",
    "Nov": "",
    "City": "Darwin",
    "Oct": "",
    "Jun": "",
    "Aug": "1",
    "Mar": "",
    "Feb": "",
    "Jan": "",
    "Jul": ""
  },
  {
    "Sep": "1",
    "Total": "1",
    "Dec": "",
    "May": "",
    "Apr": "",
    "Nov": "",
    "City": "Dassel",
    "Oct": "",
    "Jun": "",
    "Aug": "",
    "Mar": "",
    "Feb": "",
    "Jan": "",
    "Jul": ""
  },
  {
    "Sep": "",
    "Total": "1",
    "Dec": "",
    "May": "",
    "Apr": "",
    "Nov": "",
    "City": "Dawson",
    "Oct": "",
    "Jun": "1",
    "Aug": "",
    "Mar": "",
    "Feb": "",
    "Jan": "",
    "Jul": ""
  },
  {
    "Sep": "",
    "Total": "1",
    "Dec": "",
    "May": "",
    "Apr": "",
    "Nov": "",
    "City": "Dayton",
    "Oct": "",
    "Jun": "",
    "Aug": "",
    "Mar": "",
    "Feb": "",
    "Jan": "",
    "Jul": "1"
  },
  {
    "Sep": "",
    "Total": "1",
    "Dec": "",
    "May": "",
    "Apr": "",
    "Nov": "",
    "City": "Deer Creek",
    "Oct": "",
    "Jun": "",
    "Aug": "",
    "Mar": "",
    "Feb": "",
    "Jan": "",
    "Jul": "1"
  },
  {
    "Sep": "",
    "Total": "1",
    "Dec": "",
    "May": "",
    "Apr": "",
    "Nov": "",
    "City": "Deer River",
    "Oct": "",
    "Jun": "",
    "Aug": "",
    "Mar": "",
    "Feb": "",
    "Jan": "",
    "Jul": "1"
  },
  {
    "Sep": "",
    "Total": "1",
    "Dec": "",
    "May": "",
    "Apr": "",
    "Nov": "",
    "City": "Deerwood",
    "Oct": "",
    "Jun": "",
    "Aug": "1",
    "Mar": "",
    "Feb": "",
    "Jan": "",
    "Jul": ""
  },
  {
    "Sep": "",
    "Total": "1",
    "Dec": "",
    "May": "",
    "Apr": "",
    "Nov": "",
    "City": "Delano",
    "Oct": "",
    "Jun": "",
    "Aug": "",
    "Mar": "",
    "Feb": "",
    "Jan": "",
    "Jul": "1"
  },
  {
    "Sep": "2",
    "Total": "7",
    "Dec": "",
    "May": "1",
    "Apr": "",
    "Nov": "",
    "City": "Detroit Lakes",
    "Oct": "",
    "Jun": "1",
    "Aug": "2",
    "Mar": "",
    "Feb": "1",
    "Jan": "",
    "Jul": ""
  },
  {
    "Sep": "",
    "Total": "1",
    "Dec": "",
    "May": "",
    "Apr": "",
    "Nov": "",
    "City": "Dilworth",
    "Oct": "",
    "Jun": "",
    "Aug": "",
    "Mar": "",
    "Feb": "",
    "Jan": "",
    "Jul": "1"
  },
  {
    "Sep": "",
    "Total": "1",
    "Dec": "",
    "May": "",
    "Apr": "",
    "Nov": "",
    "City": "Douglas",
    "Oct": "",
    "Jun": "",
    "Aug": "1",
    "Mar": "",
    "Feb": "",
    "Jan": "",
    "Jul": ""
  },
  {
    "Sep": "14",
    "Total": "55",
    "Dec": "1",
    "May": "10",
    "Apr": "4",
    "Nov": "2",
    "City": "Duluth",
    "Oct": "6",
    "Jun": "7",
    "Aug": "7",
    "Mar": "",
    "Feb": "1",
    "Jan": "",
    "Jul": "3"
  },
  {
    "Sep": "2",
    "Total": "12",
    "Dec": "",
    "May": "3",
    "Apr": "2",
    "Nov": "",
    "City": "Eagan",
    "Oct": "1",
    "Jun": "2",
    "Aug": "1",
    "Mar": "",
    "Feb": "",
    "Jan": "",
    "Jul": "1"
  },
  {
    "Sep": "",
    "Total": "1",
    "Dec": "",
    "May": "",
    "Apr": "",
    "Nov": "",
    "City": "Eagle Lake",
    "Oct": "",
    "Jun": "",
    "Aug": "",
    "Mar": "",
    "Feb": "",
    "Jan": "",
    "Jul": "1"
  },
  {
    "Sep": "",
    "Total": "1",
    "Dec": "",
    "May": "",
    "Apr": "",
    "Nov": "",
    "City": "East Bethel",
    "Oct": "",
    "Jun": "",
    "Aug": "",
    "Mar": "",
    "Feb": "",
    "Jan": "",
    "Jul": "1"
  },
  {
    "Sep": "1",
    "Total": "3",
    "Dec": "",
    "May": "1",
    "Apr": "",
    "Nov": "",
    "City": "East Grand Forks",
    "Oct": "1",
    "Jun": "",
    "Aug": "",
    "Mar": "",
    "Feb": "",
    "Jan": "",
    "Jul": ""
  },
  {
    "Sep": "3",
    "Total": "13",
    "Dec": "",
    "May": "3",
    "Apr": "",
    "Nov": "",
    "City": "Eden Prairie",
    "Oct": "",
    "Jun": "1",
    "Aug": "3",
    "Mar": "",
    "Feb": "1",
    "Jan": "1",
    "Jul": "1"
  },
  {
    "Sep": "1",
    "Total": "2",
    "Dec": "",
    "May": "",
    "Apr": "",
    "Nov": "",
    "City": "Edina",
    "Oct": "1",
    "Jun": "",
    "Aug": "",
    "Mar": "",
    "Feb": "",
    "Jan": "",
    "Jul": ""
  },
  {
    "Sep": "",
    "Total": "1",
    "Dec": "",
    "May": "",
    "Apr": "",
    "Nov": "",
    "City": "Elgin",
    "Oct": "",
    "Jun": "1",
    "Aug": "",
    "Mar": "",
    "Feb": "",
    "Jan": "",
    "Jul": ""
  },
  {
    "Sep": "1",
    "Total": "6",
    "Dec": "",
    "May": "1",
    "Apr": "",
    "Nov": "",
    "City": "Elk River",
    "Oct": "",
    "Jun": "1",
    "Aug": "1",
    "Mar": "1",
    "Feb": "1",
    "Jan": "",
    "Jul": ""
  },
  {
    "Sep": "1",
    "Total": "1",
    "Dec": "",
    "May": "",
    "Apr": "",
    "Nov": "",
    "City": "Ellendale",
    "Oct": "",
    "Jun": "",
    "Aug": "",
    "Mar": "",
    "Feb": "",
    "Jan": "",
    "Jul": ""
  },
  {
    "Sep": "2",
    "Total": "3",
    "Dec": "",
    "May": "",
    "Apr": "",
    "Nov": "",
    "City": "Ely",
    "Oct": "",
    "Jun": "",
    "Aug": "",
    "Mar": "",
    "Feb": "",
    "Jan": "",
    "Jul": "1"
  },
  {
    "Sep": "",
    "Total": "1",
    "Dec": "",
    "May": "",
    "Apr": "",
    "Nov": "",
    "City": "Elysian",
    "Oct": "",
    "Jun": "",
    "Aug": "",
    "Mar": "",
    "Feb": "",
    "Jan": "",
    "Jul": "1"
  },
  {
    "Sep": "1",
    "Total": "6",
    "Dec": "",
    "May": "",
    "Apr": "",
    "Nov": "",
    "City": "Excelsior",
    "Oct": "",
    "Jun": "1",
    "Aug": "",
    "Mar": "1",
    "Feb": "",
    "Jan": "1",
    "Jul": "2"
  },
  {
    "Sep": "",
    "Total": "2",
    "Dec": "",
    "May": "",
    "Apr": "",
    "Nov": "",
    "City": "Eyota",
    "Oct": "",
    "Jun": "",
    "Aug": "",
    "Mar": "",
    "Feb": "",
    "Jan": "",
    "Jul": "2"
  },
  {
    "Sep": "",
    "Total": "1",
    "Dec": "",
    "May": "",
    "Apr": "",
    "Nov": "",
    "City": "Fairfax",
    "Oct": "",
    "Jun": "1",
    "Aug": "",
    "Mar": "",
    "Feb": "",
    "Jan": "",
    "Jul": ""
  },
  {
    "Sep": "1",
    "Total": "3",
    "Dec": "",
    "May": "",
    "Apr": "",
    "Nov": "",
    "City": "Fairmont",
    "Oct": "",
    "Jun": "1",
    "Aug": "",
    "Mar": "",
    "Feb": "",
    "Jan": "",
    "Jul": "1"
  },
  {
    "Sep": "1",
    "Total": "8",
    "Dec": "",
    "May": "",
    "Apr": "3",
    "Nov": "1",
    "City": "Faribault",
    "Oct": "1",
    "Jun": "1",
    "Aug": "1",
    "Mar": "",
    "Feb": "",
    "Jan": "",
    "Jul": ""
  },
  {
    "Sep": "",
    "Total": "2",
    "Dec": "",
    "May": "",
    "Apr": "",
    "Nov": "",
    "City": "Farmington",
    "Oct": "1",
    "Jun": "1",
    "Aug": "",
    "Mar": "",
    "Feb": "",
    "Jan": "",
    "Jul": ""
  },
  {
    "Sep": "2",
    "Total": "8",
    "Dec": "",
    "May": "1",
    "Apr": "",
    "Nov": "1",
    "City": "Fergus Falls",
    "Oct": "",
    "Jun": "1",
    "Aug": "1",
    "Mar": "",
    "Feb": "",
    "Jan": "",
    "Jul": "2"
  },
  {
    "Sep": "",
    "Total": "1",
    "Dec": "",
    "May": "",
    "Apr": "",
    "Nov": "",
    "City": "Floodwood",
    "Oct": "",
    "Jun": "",
    "Aug": "",
    "Mar": "",
    "Feb": "",
    "Jan": "",
    "Jul": "1"
  },
  {
    "Sep": "1",
    "Total": "2",
    "Dec": "",
    "May": "1",
    "Apr": "",
    "Nov": "",
    "City": "Forest Lake",
    "Oct": "",
    "Jun": "",
    "Aug": "",
    "Mar": "",
    "Feb": "",
    "Jan": "",
    "Jul": ""
  },
  {
    "Sep": "1",
    "Total": "1",
    "Dec": "",
    "May": "",
    "Apr": "",
    "Nov": "",
    "City": "Fort Snelling",
    "Oct": "",
    "Jun": "",
    "Aug": "",
    "Mar": "",
    "Feb": "",
    "Jan": "",
    "Jul": ""
  },
  {
    "Sep": "",
    "Total": "1",
    "Dec": "",
    "May": "",
    "Apr": "",
    "Nov": "",
    "City": "Frazee",
    "Oct": "",
    "Jun": "",
    "Aug": "",
    "Mar": "",
    "Feb": "",
    "Jan": "",
    "Jul": "1"
  },
  {
    "Sep": "",
    "Total": "4",
    "Dec": "",
    "May": "1",
    "Apr": "1",
    "Nov": "",
    "City": "Fridley",
    "Oct": "",
    "Jun": "",
    "Aug": "1",
    "Mar": "",
    "Feb": "",
    "Jan": "1",
    "Jul": ""
  },
  {
    "Sep": "1",
    "Total": "1",
    "Dec": "",
    "May": "",
    "Apr": "",
    "Nov": "",
    "City": "Frontenac",
    "Oct": "",
    "Jun": "",
    "Aug": "",
    "Mar": "",
    "Feb": "",
    "Jan": "",
    "Jul": ""
  },
  {
    "Sep": "",
    "Total": "1",
    "Dec": "",
    "May": "",
    "Apr": "",
    "Nov": "",
    "City": "Gaylord",
    "Oct": "",
    "Jun": "",
    "Aug": "1",
    "Mar": "",
    "Feb": "",
    "Jan": "",
    "Jul": ""
  },
  {
    "Sep": "",
    "Total": "1",
    "Dec": "",
    "May": "",
    "Apr": "",
    "Nov": "",
    "City": "Gibbon",
    "Oct": "",
    "Jun": "",
    "Aug": "",
    "Mar": "",
    "Feb": "",
    "Jan": "",
    "Jul": "1"
  },
  {
    "Sep": "",
    "Total": "1",
    "Dec": "",
    "May": "1",
    "Apr": "",
    "Nov": "",
    "City": "Glencoe",
    "Oct": "",
    "Jun": "",
    "Aug": "",
    "Mar": "",
    "Feb": "",
    "Jan": "",
    "Jul": ""
  },
  {
    "Sep": "",
    "Total": "3",
    "Dec": "",
    "May": "1",
    "Apr": "",
    "Nov": "",
    "City": "Glenwood",
    "Oct": "",
    "Jun": "",
    "Aug": "1",
    "Mar": "",
    "Feb": "",
    "Jan": "",
    "Jul": "1"
  },
  {
    "Sep": "",
    "Total": "2",
    "Dec": "",
    "May": "",
    "Apr": "",
    "Nov": "",
    "City": "Glyndon",
    "Oct": "",
    "Jun": "1",
    "Aug": "",
    "Mar": "",
    "Feb": "",
    "Jan": "",
    "Jul": "1"
  },
  {
    "Sep": "",
    "Total": "1",
    "Dec": "",
    "May": "",
    "Apr": "1",
    "Nov": "",
    "City": "Golden Valley",
    "Oct": "",
    "Jun": "",
    "Aug": "",
    "Mar": "",
    "Feb": "",
    "Jan": "",
    "Jul": ""
  },
  {
    "Sep": "",
    "Total": "1",
    "Dec": "",
    "May": "",
    "Apr": "",
    "Nov": "",
    "City": "Gonvick",
    "Oct": "",
    "Jun": "",
    "Aug": "",
    "Mar": "",
    "Feb": "",
    "Jan": "",
    "Jul": "1"
  },
  {
    "Sep": "",
    "Total": "1",
    "Dec": "",
    "May": "",
    "Apr": "",
    "Nov": "",
    "City": "Goodland",
    "Oct": "",
    "Jun": "",
    "Aug": "1",
    "Mar": "",
    "Feb": "",
    "Jan": "",
    "Jul": ""
  },
  {
    "Sep": "",
    "Total": "1",
    "Dec": "",
    "May": "",
    "Apr": "",
    "Nov": "",
    "City": "Goodview",
    "Oct": "",
    "Jun": "",
    "Aug": "1",
    "Mar": "",
    "Feb": "",
    "Jan": "",
    "Jul": ""
  },
  {
    "Sep": "",
    "Total": "1",
    "Dec": "",
    "May": "1",
    "Apr": "",
    "Nov": "",
    "City": "Grand Marais",
    "Oct": "",
    "Jun": "",
    "Aug": "",
    "Mar": "",
    "Feb": "",
    "Jan": "",
    "Jul": ""
  },
  {
    "Sep": "",
    "Total": "5",
    "Dec": "",
    "May": "",
    "Apr": "",
    "Nov": "",
    "City": "Grand Rapids",
    "Oct": "",
    "Jun": "1",
    "Aug": "2",
    "Mar": "",
    "Feb": "",
    "Jan": "",
    "Jul": "2"
  },
  {
    "Sep": "",
    "Total": "1",
    "Dec": "",
    "May": "",
    "Apr": "",
    "Nov": "",
    "City": "Granite Falls",
    "Oct": "",
    "Jun": "1",
    "Aug": "",
    "Mar": "",
    "Feb": "",
    "Jan": "",
    "Jul": ""
  },
  {
    "Sep": "",
    "Total": "1",
    "Dec": "",
    "May": "",
    "Apr": "",
    "Nov": "",
    "City": "Green Isle",
    "Oct": "",
    "Jun": "1",
    "Aug": "",
    "Mar": "",
    "Feb": "",
    "Jan": "",
    "Jul": ""
  },
  {
    "Sep": "1",
    "Total": "1",
    "Dec": "",
    "May": "",
    "Apr": "",
    "Nov": "",
    "City": "Hallock",
    "Oct": "",
    "Jun": "",
    "Aug": "",
    "Mar": "",
    "Feb": "",
    "Jan": "",
    "Jul": ""
  },
  {
    "Sep": "",
    "Total": "1",
    "Dec": "",
    "May": "",
    "Apr": "",
    "Nov": "",
    "City": "Hamel",
    "Oct": "",
    "Jun": "",
    "Aug": "",
    "Mar": "",
    "Feb": "1",
    "Jan": "",
    "Jul": ""
  },
  {
    "Sep": "",
    "Total": "1",
    "Dec": "",
    "May": "",
    "Apr": "",
    "Nov": "",
    "City": "Hanover",
    "Oct": "",
    "Jun": "",
    "Aug": "1",
    "Mar": "",
    "Feb": "",
    "Jan": "",
    "Jul": ""
  },
  {
    "Sep": "1",
    "Total": "6",
    "Dec": "",
    "May": "2",
    "Apr": "",
    "Nov": "1",
    "City": "Hastings",
    "Oct": "",
    "Jun": "",
    "Aug": "",
    "Mar": "",
    "Feb": "",
    "Jan": "",
    "Jul": "2"
  },
  {
    "Sep": "",
    "Total": "1",
    "Dec": "",
    "May": "",
    "Apr": "",
    "Nov": "",
    "City": "Hawley",
    "Oct": "",
    "Jun": "1",
    "Aug": "",
    "Mar": "",
    "Feb": "",
    "Jan": "",
    "Jul": ""
  },
  {
    "Sep": "",
    "Total": "2",
    "Dec": "",
    "May": "",
    "Apr": "",
    "Nov": "",
    "City": "Henning",
    "Oct": "",
    "Jun": "",
    "Aug": "",
    "Mar": "",
    "Feb": "",
    "Jan": "",
    "Jul": "2"
  },
  {
    "Sep": "1",
    "Total": "3",
    "Dec": "",
    "May": "",
    "Apr": "",
    "Nov": "",
    "City": "Hermantown",
    "Oct": "",
    "Jun": "",
    "Aug": "",
    "Mar": "1",
    "Feb": "",
    "Jan": "",
    "Jul": "1"
  },
  {
    "Sep": "",
    "Total": "1",
    "Dec": "",
    "May": "",
    "Apr": "1",
    "Nov": "",
    "City": "Hibbing",
    "Oct": "",
    "Jun": "",
    "Aug": "",
    "Mar": "",
    "Feb": "",
    "Jan": "",
    "Jul": ""
  },
  {
    "Sep": "",
    "Total": "4",
    "Dec": "",
    "May": "1",
    "Apr": "",
    "Nov": "",
    "City": "Hill City",
    "Oct": "",
    "Jun": "",
    "Aug": "1",
    "Mar": "",
    "Feb": "",
    "Jan": "",
    "Jul": "2"
  },
  {
    "Sep": "",
    "Total": "3",
    "Dec": "",
    "May": "1",
    "Apr": "",
    "Nov": "",
    "City": "Hopkins",
    "Oct": "",
    "Jun": "",
    "Aug": "",
    "Mar": "1",
    "Feb": "",
    "Jan": "",
    "Jul": "1"
  },
  {
    "Sep": "",
    "Total": "2",
    "Dec": "",
    "May": "1",
    "Apr": "",
    "Nov": "",
    "City": "Houston",
    "Oct": "1",
    "Jun": "",
    "Aug": "",
    "Mar": "",
    "Feb": "",
    "Jan": "",
    "Jul": ""
  },
  {
    "Sep": "",
    "Total": "1",
    "Dec": "",
    "May": "",
    "Apr": "",
    "Nov": "",
    "City": "Hoyt Lakes",
    "Oct": "",
    "Jun": "",
    "Aug": "",
    "Mar": "",
    "Feb": "",
    "Jan": "",
    "Jul": "1"
  },
  {
    "Sep": "",
    "Total": "3",
    "Dec": "",
    "May": "1",
    "Apr": "",
    "Nov": "",
    "City": "Hugo",
    "Oct": "1",
    "Jun": "",
    "Aug": "1",
    "Mar": "",
    "Feb": "",
    "Jan": "",
    "Jul": ""
  },
  {
    "Sep": "",
    "Total": "3",
    "Dec": "",
    "May": "",
    "Apr": "",
    "Nov": "",
    "City": "Hutchinson",
    "Oct": "1",
    "Jun": "2",
    "Aug": "",
    "Mar": "",
    "Feb": "",
    "Jan": "",
    "Jul": ""
  },
  {
    "Sep": "1",
    "Total": "6",
    "Dec": "",
    "May": "",
    "Apr": "",
    "Nov": "",
    "City": "International Falls",
    "Oct": "",
    "Jun": "",
    "Aug": "2",
    "Mar": "",
    "Feb": "",
    "Jan": "2",
    "Jul": "1"
  },
  {
    "Sep": "1",
    "Total": "1",
    "Dec": "",
    "May": "",
    "Apr": "",
    "Nov": "",
    "City": "Inver Grove Heights",
    "Oct": "",
    "Jun": "",
    "Aug": "",
    "Mar": "",
    "Feb": "",
    "Jan": "",
    "Jul": ""
  },
  {
    "Sep": "",
    "Total": "1",
    "Dec": "",
    "May": "",
    "Apr": "",
    "Nov": "",
    "City": "Isle",
    "Oct": "",
    "Jun": "",
    "Aug": "",
    "Mar": "",
    "Feb": "",
    "Jan": "",
    "Jul": "1"
  },
  {
    "Sep": "",
    "Total": "2",
    "Dec": "",
    "May": "",
    "Apr": "",
    "Nov": "",
    "City": "Jackson",
    "Oct": "",
    "Jun": "2",
    "Aug": "",
    "Mar": "",
    "Feb": "",
    "Jan": "",
    "Jul": ""
  },
  {
    "Sep": "",
    "Total": "3",
    "Dec": "",
    "May": "",
    "Apr": "",
    "Nov": "",
    "City": "Janesville",
    "Oct": "",
    "Jun": "1",
    "Aug": "",
    "Mar": "2",
    "Feb": "",
    "Jan": "",
    "Jul": ""
  },
  {
    "Sep": "",
    "Total": "1",
    "Dec": "",
    "May": "",
    "Apr": "",
    "Nov": "",
    "City": "Kasson",
    "Oct": "",
    "Jun": "",
    "Aug": "1",
    "Mar": "",
    "Feb": "",
    "Jan": "",
    "Jul": ""
  },
  {
    "Sep": "1",
    "Total": "1",
    "Dec": "",
    "May": "",
    "Apr": "",
    "Nov": "",
    "City": "Kensington",
    "Oct": "",
    "Jun": "",
    "Aug": "",
    "Mar": "",
    "Feb": "",
    "Jan": "",
    "Jul": ""
  },
  {
    "Sep": "",
    "Total": "1",
    "Dec": "",
    "May": "",
    "Apr": "",
    "Nov": "",
    "City": "Kenyon",
    "Oct": "",
    "Jun": "",
    "Aug": "",
    "Mar": "",
    "Feb": "1",
    "Jan": "",
    "Jul": ""
  },
  {
    "Sep": "",
    "Total": "1",
    "Dec": "",
    "May": "",
    "Apr": "",
    "Nov": "",
    "City": "Kerkhoven",
    "Oct": "",
    "Jun": "",
    "Aug": "",
    "Mar": "",
    "Feb": "",
    "Jan": "",
    "Jul": "1"
  },
  {
    "Sep": "1",
    "Total": "1",
    "Dec": "",
    "May": "",
    "Apr": "",
    "Nov": "",
    "City": "Kilkenny",
    "Oct": "",
    "Jun": "",
    "Aug": "",
    "Mar": "",
    "Feb": "",
    "Jan": "",
    "Jul": ""
  },
  {
    "Sep": "",
    "Total": "3",
    "Dec": "",
    "May": "",
    "Apr": "",
    "Nov": "",
    "City": "Kimball",
    "Oct": "",
    "Jun": "1",
    "Aug": "1",
    "Mar": "",
    "Feb": "",
    "Jan": "",
    "Jul": "1"
  },
  {
    "Sep": "1",
    "Total": "1",
    "Dec": "",
    "May": "",
    "Apr": "",
    "Nov": "",
    "City": "La Crescent",
    "Oct": "",
    "Jun": "",
    "Aug": "",
    "Mar": "",
    "Feb": "",
    "Jan": "",
    "Jul": ""
  },
  {
    "Sep": "",
    "Total": "1",
    "Dec": "",
    "May": "",
    "Apr": "",
    "Nov": "",
    "City": "Lake Benton",
    "Oct": "1",
    "Jun": "",
    "Aug": "",
    "Mar": "",
    "Feb": "",
    "Jan": "",
    "Jul": ""
  },
  {
    "Sep": "",
    "Total": "1",
    "Dec": "",
    "May": "1",
    "Apr": "",
    "Nov": "",
    "City": "Lake Bronson",
    "Oct": "",
    "Jun": "",
    "Aug": "",
    "Mar": "",
    "Feb": "",
    "Jan": "",
    "Jul": ""
  },
  {
    "Sep": "",
    "Total": "2",
    "Dec": "",
    "May": "",
    "Apr": "",
    "Nov": "",
    "City": "Lake City",
    "Oct": "",
    "Jun": "1",
    "Aug": "1",
    "Mar": "",
    "Feb": "",
    "Jan": "",
    "Jul": ""
  },
  {
    "Sep": "",
    "Total": "1",
    "Dec": "",
    "May": "",
    "Apr": "",
    "Nov": "",
    "City": "Lake Crystal",
    "Oct": "",
    "Jun": "1",
    "Aug": "",
    "Mar": "",
    "Feb": "",
    "Jan": "",
    "Jul": ""
  },
  {
    "Sep": "1",
    "Total": "5",
    "Dec": "",
    "May": "1",
    "Apr": "",
    "Nov": "",
    "City": "Lake Elmo",
    "Oct": "2",
    "Jun": "",
    "Aug": "",
    "Mar": "",
    "Feb": "",
    "Jan": "1",
    "Jul": ""
  },
  {
    "Sep": "",
    "Total": "7",
    "Dec": "",
    "May": "2",
    "Apr": "1",
    "Nov": "",
    "City": "Lakeville",
    "Oct": "1",
    "Jun": "1",
    "Aug": "1",
    "Mar": "",
    "Feb": "",
    "Jan": "1",
    "Jul": ""
  },
  {
    "Sep": "",
    "Total": "2",
    "Dec": "",
    "May": "",
    "Apr": "",
    "Nov": "",
    "City": "Lanesboro",
    "Oct": "",
    "Jun": "1",
    "Aug": "1",
    "Mar": "",
    "Feb": "",
    "Jan": "",
    "Jul": ""
  },
  {
    "Sep": "1",
    "Total": "1",
    "Dec": "",
    "May": "",
    "Apr": "",
    "Nov": "",
    "City": "Lauderdale",
    "Oct": "",
    "Jun": "",
    "Aug": "",
    "Mar": "",
    "Feb": "",
    "Jan": "",
    "Jul": ""
  },
  {
    "Sep": "",
    "Total": "1",
    "Dec": "",
    "May": "",
    "Apr": "",
    "Nov": "",
    "City": "Le Roy",
    "Oct": "",
    "Jun": "",
    "Aug": "",
    "Mar": "",
    "Feb": "",
    "Jan": "",
    "Jul": "1"
  },
  {
    "Sep": "",
    "Total": "1",
    "Dec": "",
    "May": "",
    "Apr": "",
    "Nov": "",
    "City": "Le Sueur",
    "Oct": "",
    "Jun": "",
    "Aug": "1",
    "Mar": "",
    "Feb": "",
    "Jan": "",
    "Jul": ""
  },
  {
    "Sep": "",
    "Total": "1",
    "Dec": "",
    "May": "",
    "Apr": "1",
    "Nov": "",
    "City": "Lewiston",
    "Oct": "",
    "Jun": "",
    "Aug": "",
    "Mar": "",
    "Feb": "",
    "Jan": "",
    "Jul": ""
  },
  {
    "Sep": "",
    "Total": "1",
    "Dec": "",
    "May": "",
    "Apr": "",
    "Nov": "",
    "City": "Lexington",
    "Oct": "",
    "Jun": "",
    "Aug": "",
    "Mar": "",
    "Feb": "",
    "Jan": "",
    "Jul": "1"
  },
  {
    "Sep": "1",
    "Total": "2",
    "Dec": "",
    "May": "",
    "Apr": "1",
    "Nov": "",
    "City": "Lindstrom",
    "Oct": "",
    "Jun": "",
    "Aug": "",
    "Mar": "",
    "Feb": "",
    "Jan": "",
    "Jul": ""
  },
  {
    "Sep": "2",
    "Total": "7",
    "Dec": "",
    "May": "",
    "Apr": "",
    "Nov": "",
    "City": "Lino Lakes",
    "Oct": "",
    "Jun": "2",
    "Aug": "3",
    "Mar": "",
    "Feb": "",
    "Jan": "",
    "Jul": ""
  },
  {
    "Sep": "",
    "Total": "2",
    "Dec": "",
    "May": "1",
    "Apr": "",
    "Nov": "",
    "City": "Litchfield",
    "Oct": "",
    "Jun": "",
    "Aug": "",
    "Mar": "",
    "Feb": "",
    "Jan": "",
    "Jul": "1"
  },
  {
    "Sep": "",
    "Total": "2",
    "Dec": "",
    "May": "1",
    "Apr": "",
    "Nov": "",
    "City": "Little Falls",
    "Oct": "",
    "Jun": "1",
    "Aug": "",
    "Mar": "",
    "Feb": "",
    "Jan": "",
    "Jul": ""
  },
  {
    "Sep": "",
    "Total": "4",
    "Dec": "",
    "May": "",
    "Apr": "",
    "Nov": "",
    "City": "Long Lake",
    "Oct": "1",
    "Jun": "1",
    "Aug": "1",
    "Mar": "",
    "Feb": "",
    "Jan": "",
    "Jul": "1"
  },
  {
    "Sep": "",
    "Total": "2",
    "Dec": "",
    "May": "1",
    "Apr": "",
    "Nov": "",
    "City": "Long Prairie",
    "Oct": "",
    "Jun": "",
    "Aug": "",
    "Mar": "",
    "Feb": "",
    "Jan": "",
    "Jul": "1"
  },
  {
    "Sep": "",
    "Total": "1",
    "Dec": "",
    "May": "1",
    "Apr": "",
    "Nov": "",
    "City": "Longville",
    "Oct": "",
    "Jun": "",
    "Aug": "",
    "Mar": "",
    "Feb": "",
    "Jan": "",
    "Jul": ""
  },
  {
    "Sep": "",
    "Total": "1",
    "Dec": "",
    "May": "",
    "Apr": "",
    "Nov": "",
    "City": "Lonsdale",
    "Oct": "1",
    "Jun": "",
    "Aug": "",
    "Mar": "",
    "Feb": "",
    "Jan": "",
    "Jul": ""
  },
  {
    "Sep": "2",
    "Total": "3",
    "Dec": "",
    "May": "1",
    "Apr": "",
    "Nov": "",
    "City": "Lutsen",
    "Oct": "",
    "Jun": "",
    "Aug": "",
    "Mar": "",
    "Feb": "",
    "Jan": "",
    "Jul": ""
  },
  {
    "Sep": "1",
    "Total": "2",
    "Dec": "",
    "May": "",
    "Apr": "",
    "Nov": "",
    "City": "Madelia",
    "Oct": "",
    "Jun": "",
    "Aug": "",
    "Mar": "",
    "Feb": "",
    "Jan": "",
    "Jul": "1"
  },
  {
    "Sep": "",
    "Total": "1",
    "Dec": "",
    "May": "",
    "Apr": "",
    "Nov": "",
    "City": "Madison",
    "Oct": "",
    "Jun": "1",
    "Aug": "",
    "Mar": "",
    "Feb": "",
    "Jan": "",
    "Jul": ""
  },
  {
    "Sep": "",
    "Total": "1",
    "Dec": "",
    "May": "",
    "Apr": "",
    "Nov": "",
    "City": "Mahnomen",
    "Oct": "",
    "Jun": "",
    "Aug": "",
    "Mar": "",
    "Feb": "",
    "Jan": "1",
    "Jul": ""
  },
  {
    "Sep": "",
    "Total": "2",
    "Dec": "",
    "May": "",
    "Apr": "1",
    "Nov": "",
    "City": "Mahtomedi",
    "Oct": "",
    "Jun": "",
    "Aug": "",
    "Mar": "",
    "Feb": "1",
    "Jan": "",
    "Jul": ""
  },
  {
    "Sep": "1",
    "Total": "19",
    "Dec": "2",
    "May": "2",
    "Apr": "2",
    "Nov": "",
    "City": "Mankato",
    "Oct": "6",
    "Jun": "1",
    "Aug": "3",
    "Mar": "2",
    "Feb": "",
    "Jan": "",
    "Jul": ""
  },
  {
    "Sep": "10",
    "Total": "25",
    "Dec": "2",
    "May": "3",
    "Apr": "",
    "Nov": "",
    "City": "Maple Grove",
    "Oct": "3",
    "Jun": "1",
    "Aug": "3",
    "Mar": "2",
    "Feb": "1",
    "Jan": "",
    "Jul": ""
  },
  {
    "Sep": "",
    "Total": "1",
    "Dec": "",
    "May": "",
    "Apr": "",
    "Nov": "",
    "City": "Maple Lake",
    "Oct": "",
    "Jun": "",
    "Aug": "",
    "Mar": "1",
    "Feb": "",
    "Jan": "",
    "Jul": ""
  },
  {
    "Sep": "",
    "Total": "1",
    "Dec": "",
    "May": "",
    "Apr": "",
    "Nov": "",
    "City": "Maple Plain",
    "Oct": "",
    "Jun": "",
    "Aug": "1",
    "Mar": "",
    "Feb": "",
    "Jan": "",
    "Jul": ""
  },
  {
    "Sep": "2",
    "Total": "4",
    "Dec": "",
    "May": "",
    "Apr": "",
    "Nov": "",
    "City": "Maplewood",
    "Oct": "",
    "Jun": "2",
    "Aug": "",
    "Mar": "",
    "Feb": "",
    "Jan": "",
    "Jul": ""
  },
  {
    "Sep": "1",
    "Total": "2",
    "Dec": "",
    "May": "",
    "Apr": "",
    "Nov": "",
    "City": "Marine on St. Croix",
    "Oct": "",
    "Jun": "",
    "Aug": "",
    "Mar": "",
    "Feb": "",
    "Jan": "",
    "Jul": "1"
  },
  {
    "Sep": "",
    "Total": "2",
    "Dec": "",
    "May": "",
    "Apr": "1",
    "Nov": "",
    "City": "Marshall",
    "Oct": "",
    "Jun": "1",
    "Aug": "",
    "Mar": "",
    "Feb": "",
    "Jan": "",
    "Jul": ""
  },
  {
    "Sep": "",
    "Total": "2",
    "Dec": "",
    "May": "1",
    "Apr": "",
    "Nov": "",
    "City": "McGregor",
    "Oct": "",
    "Jun": "",
    "Aug": "1",
    "Mar": "",
    "Feb": "",
    "Jan": "",
    "Jul": ""
  },
  {
    "Sep": "",
    "Total": "1",
    "Dec": "",
    "May": "",
    "Apr": "",
    "Nov": "",
    "City": "Medford",
    "Oct": "",
    "Jun": "1",
    "Aug": "",
    "Mar": "",
    "Feb": "",
    "Jan": "",
    "Jul": ""
  },
  {
    "Sep": "",
    "Total": "1",
    "Dec": "",
    "May": "",
    "Apr": "",
    "Nov": "",
    "City": "Melrose",
    "Oct": "",
    "Jun": "1",
    "Aug": "",
    "Mar": "",
    "Feb": "",
    "Jan": "",
    "Jul": ""
  },
  {
    "Sep": "",
    "Total": "1",
    "Dec": "",
    "May": "",
    "Apr": "",
    "Nov": "",
    "City": "Mendota",
    "Oct": "",
    "Jun": "",
    "Aug": "1",
    "Mar": "",
    "Feb": "",
    "Jan": "",
    "Jul": ""
  },
  {
    "Sep": "1",
    "Total": "4",
    "Dec": "",
    "May": "2",
    "Apr": "",
    "Nov": "",
    "City": "Mendota Heights",
    "Oct": "",
    "Jun": "1",
    "Aug": "",
    "Mar": "",
    "Feb": "",
    "Jan": "",
    "Jul": ""
  },
  {
    "Sep": "1",
    "Total": "2",
    "Dec": "",
    "May": "1",
    "Apr": "",
    "Nov": "",
    "City": "Milaca",
    "Oct": "",
    "Jun": "",
    "Aug": "",
    "Mar": "",
    "Feb": "",
    "Jan": "",
    "Jul": ""
  },
  {
    "Sep": "13",
    "Total": "128",
    "Dec": "3",
    "May": "16",
    "Apr": "15",
    "Nov": "6",
    "City": "Minneapolis",
    "Oct": "16",
    "Jun": "17",
    "Aug": "19",
    "Mar": "3",
    "Feb": "6",
    "Jan": "3",
    "Jul": "11"
  },
  {
    "Sep": "2",
    "Total": "7",
    "Dec": "",
    "May": "1",
    "Apr": "1",
    "Nov": "1",
    "City": "Minnetonka",
    "Oct": "1",
    "Jun": "1",
    "Aug": "",
    "Mar": "",
    "Feb": "",
    "Jan": "",
    "Jul": ""
  },
  {
    "Sep": "",
    "Total": "2",
    "Dec": "",
    "May": "1",
    "Apr": "",
    "Nov": "",
    "City": "Montgomery",
    "Oct": "",
    "Jun": "",
    "Aug": "",
    "Mar": "",
    "Feb": "",
    "Jan": "",
    "Jul": "1"
  },
  {
    "Sep": "2",
    "Total": "8",
    "Dec": "",
    "May": "2",
    "Apr": "",
    "Nov": "",
    "City": "Monticello",
    "Oct": "1",
    "Jun": "",
    "Aug": "",
    "Mar": "1",
    "Feb": "",
    "Jan": "",
    "Jul": "2"
  },
  {
    "Sep": "",
    "Total": "1",
    "Dec": "",
    "May": "",
    "Apr": "1",
    "Nov": "",
    "City": "Montrose",
    "Oct": "",
    "Jun": "",
    "Aug": "",
    "Mar": "",
    "Feb": "",
    "Jan": "",
    "Jul": ""
  },
  {
    "Sep": "1",
    "Total": "5",
    "Dec": "",
    "May": "",
    "Apr": "",
    "Nov": "",
    "City": "Moorhead",
    "Oct": "1",
    "Jun": "2",
    "Aug": "1",
    "Mar": "",
    "Feb": "",
    "Jan": "",
    "Jul": ""
  },
  {
    "Sep": "",
    "Total": "2",
    "Dec": "",
    "May": "1",
    "Apr": "",
    "Nov": "",
    "City": "Moose Lake",
    "Oct": "",
    "Jun": "",
    "Aug": "",
    "Mar": "",
    "Feb": "",
    "Jan": "",
    "Jul": "1"
  },
  {
    "Sep": "",
    "Total": "1",
    "Dec": "",
    "May": "",
    "Apr": "",
    "Nov": "",
    "City": "Mora",
    "Oct": "",
    "Jun": "",
    "Aug": "1",
    "Mar": "",
    "Feb": "",
    "Jan": "",
    "Jul": ""
  },
  {
    "Sep": "",
    "Total": "2",
    "Dec": "",
    "May": "",
    "Apr": "1",
    "Nov": "",
    "City": "Morris",
    "Oct": "",
    "Jun": "",
    "Aug": "",
    "Mar": "",
    "Feb": "",
    "Jan": "",
    "Jul": "1"
  },
  {
    "Sep": "",
    "Total": "1",
    "Dec": "",
    "May": "",
    "Apr": "",
    "Nov": "",
    "City": "Morton",
    "Oct": "",
    "Jun": "",
    "Aug": "",
    "Mar": "",
    "Feb": "",
    "Jan": "",
    "Jul": "1"
  },
  {
    "Sep": "1",
    "Total": "1",
    "Dec": "",
    "May": "",
    "Apr": "",
    "Nov": "",
    "City": "Mound",
    "Oct": "",
    "Jun": "",
    "Aug": "",
    "Mar": "",
    "Feb": "",
    "Jan": "",
    "Jul": ""
  },
  {
    "Sep": "",
    "Total": "2",
    "Dec": "",
    "May": "",
    "Apr": "1",
    "Nov": "",
    "City": "Mounds View",
    "Oct": "",
    "Jun": "",
    "Aug": "1",
    "Mar": "",
    "Feb": "",
    "Jan": "",
    "Jul": ""
  },
  {
    "Sep": "",
    "Total": "1",
    "Dec": "",
    "May": "",
    "Apr": "",
    "Nov": "",
    "City": "Mountain Iron",
    "Oct": "",
    "Jun": "",
    "Aug": "1",
    "Mar": "",
    "Feb": "",
    "Jan": "",
    "Jul": ""
  },
  {
    "Sep": "",
    "Total": "1",
    "Dec": "",
    "May": "",
    "Apr": "",
    "Nov": "",
    "City": "Mountain Lake",
    "Oct": "",
    "Jun": "1",
    "Aug": "",
    "Mar": "",
    "Feb": "",
    "Jan": "",
    "Jul": ""
  },
  {
    "Sep": "",
    "Total": "1",
    "Dec": "",
    "May": "",
    "Apr": "",
    "Nov": "",
    "City": "Nashwauk",
    "Oct": "",
    "Jun": "",
    "Aug": "",
    "Mar": "",
    "Feb": "",
    "Jan": "",
    "Jul": "1"
  },
  {
    "Sep": "",
    "Total": "1",
    "Dec": "",
    "May": "",
    "Apr": "",
    "Nov": "",
    "City": "Nerstrand",
    "Oct": "1",
    "Jun": "",
    "Aug": "",
    "Mar": "",
    "Feb": "",
    "Jan": "",
    "Jul": ""
  },
  {
    "Sep": "",
    "Total": "2",
    "Dec": "",
    "May": "",
    "Apr": "",
    "Nov": "",
    "City": "Nevis",
    "Oct": "",
    "Jun": "",
    "Aug": "1",
    "Mar": "",
    "Feb": "",
    "Jan": "",
    "Jul": "1"
  },
  {
    "Sep": "1",
    "Total": "6",
    "Dec": "",
    "May": "1",
    "Apr": "",
    "Nov": "",
    "City": "New Brighton",
    "Oct": "",
    "Jun": "1",
    "Aug": "2",
    "Mar": "",
    "Feb": "1",
    "Jan": "",
    "Jul": ""
  },
  {
    "Sep": "1",
    "Total": "2",
    "Dec": "",
    "May": "1",
    "Apr": "",
    "Nov": "",
    "City": "New London",
    "Oct": "",
    "Jun": "",
    "Aug": "",
    "Mar": "",
    "Feb": "",
    "Jan": "",
    "Jul": ""
  },
  {
    "Sep": "",
    "Total": "1",
    "Dec": "",
    "May": "1",
    "Apr": "",
    "Nov": "",
    "City": "New Prague",
    "Oct": "",
    "Jun": "",
    "Aug": "",
    "Mar": "",
    "Feb": "",
    "Jan": "",
    "Jul": ""
  },
  {
    "Sep": "2",
    "Total": "6",
    "Dec": "1",
    "May": "1",
    "Apr": "",
    "Nov": "",
    "City": "New Ulm",
    "Oct": "1",
    "Jun": "",
    "Aug": "",
    "Mar": "",
    "Feb": "",
    "Jan": "",
    "Jul": "1"
  },
  {
    "Sep": "",
    "Total": "1",
    "Dec": "",
    "May": "",
    "Apr": "",
    "Nov": "",
    "City": "Nicollet",
    "Oct": "",
    "Jun": "1",
    "Aug": "",
    "Mar": "",
    "Feb": "",
    "Jan": "",
    "Jul": ""
  },
  {
    "Sep": "",
    "Total": "3",
    "Dec": "",
    "May": "",
    "Apr": "2",
    "Nov": "",
    "City": "Nisswa",
    "Oct": "",
    "Jun": "",
    "Aug": "",
    "Mar": "",
    "Feb": "",
    "Jan": "",
    "Jul": "1"
  },
  {
    "Sep": "",
    "Total": "1",
    "Dec": "",
    "May": "1",
    "Apr": "",
    "Nov": "",
    "City": "North Branch",
    "Oct": "",
    "Jun": "",
    "Aug": "",
    "Mar": "",
    "Feb": "",
    "Jan": "",
    "Jul": ""
  },
  {
    "Sep": "1",
    "Total": "4",
    "Dec": "",
    "May": "1",
    "Apr": "",
    "Nov": "1",
    "City": "North Mankato",
    "Oct": "",
    "Jun": "",
    "Aug": "1",
    "Mar": "",
    "Feb": "",
    "Jan": "",
    "Jul": ""
  },
  {
    "Sep": "1",
    "Total": "2",
    "Dec": "",
    "May": "",
    "Apr": "",
    "Nov": "",
    "City": "North St. Paul",
    "Oct": "",
    "Jun": "",
    "Aug": "",
    "Mar": "",
    "Feb": "",
    "Jan": "",
    "Jul": "1"
  },
  {
    "Sep": "1",
    "Total": "8",
    "Dec": "1",
    "May": "2",
    "Apr": "",
    "Nov": "",
    "City": "Northfield",
    "Oct": "2",
    "Jun": "",
    "Aug": "",
    "Mar": "",
    "Feb": "",
    "Jan": "1",
    "Jul": "1"
  },
  {
    "Sep": "",
    "Total": "1",
    "Dec": "",
    "May": "",
    "Apr": "",
    "Nov": "",
    "City": "Norwood Young America",
    "Oct": "",
    "Jun": "",
    "Aug": "1",
    "Mar": "",
    "Feb": "",
    "Jan": "",
    "Jul": ""
  },
  {
    "Sep": "1",
    "Total": "2",
    "Dec": "",
    "May": "",
    "Apr": "",
    "Nov": "",
    "City": "Oak Grove",
    "Oct": "",
    "Jun": "1",
    "Aug": "",
    "Mar": "",
    "Feb": "",
    "Jan": "",
    "Jul": ""
  },
  {
    "Sep": "",
    "Total": "1",
    "Dec": "",
    "May": "",
    "Apr": "",
    "Nov": "",
    "City": "Oak Park Heights",
    "Oct": "",
    "Jun": "1",
    "Aug": "",
    "Mar": "",
    "Feb": "",
    "Jan": "",
    "Jul": ""
  },
  {
    "Sep": "1",
    "Total": "2",
    "Dec": "",
    "May": "",
    "Apr": "",
    "Nov": "",
    "City": "Oakdale",
    "Oct": "",
    "Jun": "1",
    "Aug": "",
    "Mar": "",
    "Feb": "",
    "Jan": "",
    "Jul": ""
  },
  {
    "Sep": "",
    "Total": "1",
    "Dec": "",
    "May": "",
    "Apr": "",
    "Nov": "",
    "City": "Olivia",
    "Oct": "",
    "Jun": "",
    "Aug": "",
    "Mar": "",
    "Feb": "",
    "Jan": "",
    "Jul": "1"
  },
  {
    "Sep": "",
    "Total": "1",
    "Dec": "",
    "May": "1",
    "Apr": "",
    "Nov": "",
    "City": "Orono",
    "Oct": "",
    "Jun": "",
    "Aug": "",
    "Mar": "",
    "Feb": "",
    "Jan": "",
    "Jul": ""
  },
  {
    "Sep": "",
    "Total": "1",
    "Dec": "",
    "May": "",
    "Apr": "",
    "Nov": "",
    "City": "Orr",
    "Oct": "",
    "Jun": "",
    "Aug": "",
    "Mar": "",
    "Feb": "",
    "Jan": "",
    "Jul": "1"
  },
  {
    "Sep": "1",
    "Total": "2",
    "Dec": "",
    "May": "1",
    "Apr": "",
    "Nov": "",
    "City": "Osakis",
    "Oct": "",
    "Jun": "",
    "Aug": "",
    "Mar": "",
    "Feb": "",
    "Jan": "",
    "Jul": ""
  },
  {
    "Sep": "1",
    "Total": "1",
    "Dec": "",
    "May": "",
    "Apr": "",
    "Nov": "",
    "City": "Osseo",
    "Oct": "",
    "Jun": "",
    "Aug": "",
    "Mar": "",
    "Feb": "",
    "Jan": "",
    "Jul": ""
  },
  {
    "Sep": "",
    "Total": "2",
    "Dec": "",
    "May": "",
    "Apr": "",
    "Nov": "1",
    "City": "Otsego",
    "Oct": "",
    "Jun": "1",
    "Aug": "",
    "Mar": "",
    "Feb": "",
    "Jan": "",
    "Jul": ""
  },
  {
    "Sep": "",
    "Total": "5",
    "Dec": "",
    "May": "2",
    "Apr": "",
    "Nov": "",
    "City": "Owatonna",
    "Oct": "1",
    "Jun": "",
    "Aug": "2",
    "Mar": "",
    "Feb": "",
    "Jan": "",
    "Jul": ""
  },
  {
    "Sep": "1",
    "Total": "3",
    "Dec": "",
    "May": "",
    "Apr": "",
    "Nov": "",
    "City": "Park Rapids",
    "Oct": "",
    "Jun": "",
    "Aug": "1",
    "Mar": "",
    "Feb": "",
    "Jan": "",
    "Jul": "1"
  },
  {
    "Sep": "",
    "Total": "1",
    "Dec": "",
    "May": "",
    "Apr": "",
    "Nov": "",
    "City": "Paynesville",
    "Oct": "",
    "Jun": "1",
    "Aug": "",
    "Mar": "",
    "Feb": "",
    "Jan": "",
    "Jul": ""
  },
  {
    "Sep": "",
    "Total": "1",
    "Dec": "",
    "May": "",
    "Apr": "",
    "Nov": "",
    "City": "Pelican Rapids",
    "Oct": "",
    "Jun": "1",
    "Aug": "",
    "Mar": "",
    "Feb": "",
    "Jan": "",
    "Jul": ""
  },
  {
    "Sep": "",
    "Total": "1",
    "Dec": "",
    "May": "",
    "Apr": "",
    "Nov": "",
    "City": "Pequot Lakes",
    "Oct": "",
    "Jun": "",
    "Aug": "1",
    "Mar": "",
    "Feb": "",
    "Jan": "",
    "Jul": ""
  },
  {
    "Sep": "",
    "Total": "6",
    "Dec": "",
    "May": "",
    "Apr": "",
    "Nov": "",
    "City": "Perham",
    "Oct": "",
    "Jun": "4",
    "Aug": "",
    "Mar": "",
    "Feb": "1",
    "Jan": "",
    "Jul": "1"
  },
  {
    "Sep": "",
    "Total": "2",
    "Dec": "",
    "May": "1",
    "Apr": "",
    "Nov": "",
    "City": "Pierz",
    "Oct": "",
    "Jun": "",
    "Aug": "1",
    "Mar": "",
    "Feb": "",
    "Jan": "",
    "Jul": ""
  },
  {
    "Sep": "2",
    "Total": "2",
    "Dec": "",
    "May": "",
    "Apr": "",
    "Nov": "",
    "City": "Pillager",
    "Oct": "",
    "Jun": "",
    "Aug": "",
    "Mar": "",
    "Feb": "",
    "Jan": "",
    "Jul": ""
  },
  {
    "Sep": "",
    "Total": "1",
    "Dec": "",
    "May": "",
    "Apr": "",
    "Nov": "",
    "City": "Pine Island",
    "Oct": "",
    "Jun": "1",
    "Aug": "",
    "Mar": "",
    "Feb": "",
    "Jan": "",
    "Jul": ""
  },
  {
    "Sep": "",
    "Total": "1",
    "Dec": "",
    "May": "",
    "Apr": "",
    "Nov": "",
    "City": "Plainview",
    "Oct": "",
    "Jun": "",
    "Aug": "1",
    "Mar": "",
    "Feb": "",
    "Jan": "",
    "Jul": ""
  },
  {
    "Sep": "2",
    "Total": "8",
    "Dec": "",
    "May": "",
    "Apr": "2",
    "Nov": "",
    "City": "Plymouth",
    "Oct": "1",
    "Jun": "2",
    "Aug": "1",
    "Mar": "",
    "Feb": "",
    "Jan": "",
    "Jul": ""
  },
  {
    "Sep": "",
    "Total": "1",
    "Dec": "",
    "May": "1",
    "Apr": "",
    "Nov": "",
    "City": "Preston",
    "Oct": "",
    "Jun": "",
    "Aug": "",
    "Mar": "",
    "Feb": "",
    "Jan": "",
    "Jul": ""
  },
  {
    "Sep": "",
    "Total": "3",
    "Dec": "",
    "May": "",
    "Apr": "",
    "Nov": "",
    "City": "Princeton",
    "Oct": "1",
    "Jun": "1",
    "Aug": "1",
    "Mar": "",
    "Feb": "",
    "Jan": "",
    "Jul": ""
  },
  {
    "Sep": "",
    "Total": "4",
    "Dec": "",
    "May": "1",
    "Apr": "1",
    "Nov": "1",
    "City": "Prior Lake",
    "Oct": "",
    "Jun": "",
    "Aug": "1",
    "Mar": "",
    "Feb": "",
    "Jan": "",
    "Jul": ""
  },
  {
    "Sep": "1",
    "Total": "3",
    "Dec": "",
    "May": "",
    "Apr": "",
    "Nov": "",
    "City": "Ramsey",
    "Oct": "",
    "Jun": "2",
    "Aug": "",
    "Mar": "",
    "Feb": "",
    "Jan": "",
    "Jul": ""
  },
  {
    "Sep": "",
    "Total": "1",
    "Dec": "",
    "May": "",
    "Apr": "",
    "Nov": "",
    "City": "Raymond",
    "Oct": "",
    "Jun": "",
    "Aug": "1",
    "Mar": "",
    "Feb": "",
    "Jan": "",
    "Jul": ""
  },
  {
    "Sep": "",
    "Total": "6",
    "Dec": "",
    "May": "2",
    "Apr": "",
    "Nov": "",
    "City": "Red Wing",
    "Oct": "",
    "Jun": "",
    "Aug": "3",
    "Mar": "",
    "Feb": "",
    "Jan": "",
    "Jul": "1"
  },
  {
    "Sep": "1",
    "Total": "2",
    "Dec": "",
    "May": "",
    "Apr": "",
    "Nov": "",
    "City": "Redwood Falls",
    "Oct": "",
    "Jun": "1",
    "Aug": "",
    "Mar": "",
    "Feb": "",
    "Jan": "",
    "Jul": ""
  },
  {
    "Sep": "",
    "Total": "1",
    "Dec": "",
    "May": "",
    "Apr": "",
    "Nov": "",
    "City": "Renville",
    "Oct": "",
    "Jun": "",
    "Aug": "1",
    "Mar": "",
    "Feb": "",
    "Jan": "",
    "Jul": ""
  },
  {
    "Sep": "1",
    "Total": "5",
    "Dec": "",
    "May": "1",
    "Apr": "",
    "Nov": "1",
    "City": "Richfield",
    "Oct": "",
    "Jun": "1",
    "Aug": "1",
    "Mar": "",
    "Feb": "",
    "Jan": "",
    "Jul": ""
  },
  {
    "Sep": "",
    "Total": "1",
    "Dec": "",
    "May": "1",
    "Apr": "",
    "Nov": "",
    "City": "Robbinsdale",
    "Oct": "",
    "Jun": "",
    "Aug": "",
    "Mar": "",
    "Feb": "",
    "Jan": "",
    "Jul": ""
  },
  {
    "Sep": "6",
    "Total": "50",
    "Dec": "2",
    "May": "7",
    "Apr": "1",
    "Nov": "2",
    "City": "Rochester",
    "Oct": "4",
    "Jun": "14",
    "Aug": "5",
    "Mar": "2",
    "Feb": "",
    "Jan": "",
    "Jul": "7"
  },
  {
    "Sep": "2",
    "Total": "5",
    "Dec": "",
    "May": "",
    "Apr": "1",
    "Nov": "",
    "City": "Rockford",
    "Oct": "",
    "Jun": "1",
    "Aug": "1",
    "Mar": "",
    "Feb": "",
    "Jan": "",
    "Jul": ""
  },
  {
    "Sep": "",
    "Total": "2",
    "Dec": "",
    "May": "",
    "Apr": "1",
    "Nov": "",
    "City": "Rogers",
    "Oct": "",
    "Jun": "",
    "Aug": "1",
    "Mar": "",
    "Feb": "",
    "Jan": "",
    "Jul": ""
  },
  {
    "Sep": "",
    "Total": "1",
    "Dec": "",
    "May": "",
    "Apr": "",
    "Nov": "",
    "City": "Rollingstone",
    "Oct": "",
    "Jun": "",
    "Aug": "1",
    "Mar": "",
    "Feb": "",
    "Jan": "",
    "Jul": ""
  },
  {
    "Sep": "1",
    "Total": "6",
    "Dec": "",
    "May": "",
    "Apr": "1",
    "Nov": "",
    "City": "Rosemount",
    "Oct": "",
    "Jun": "2",
    "Aug": "1",
    "Mar": "",
    "Feb": "",
    "Jan": "",
    "Jul": "1"
  },
  {
    "Sep": "",
    "Total": "6",
    "Dec": "",
    "May": "1",
    "Apr": "",
    "Nov": "1",
    "City": "Roseville",
    "Oct": "1",
    "Jun": "1",
    "Aug": "1",
    "Mar": "",
    "Feb": "",
    "Jan": "",
    "Jul": "1"
  },
  {
    "Sep": "1",
    "Total": "6",
    "Dec": "",
    "May": "1",
    "Apr": "",
    "Nov": "",
    "City": "Rush City",
    "Oct": "1",
    "Jun": "",
    "Aug": "3",
    "Mar": "",
    "Feb": "",
    "Jan": "",
    "Jul": ""
  },
  {
    "Sep": "",
    "Total": "1",
    "Dec": "",
    "May": "",
    "Apr": "",
    "Nov": "",
    "City": "Rushford",
    "Oct": "1",
    "Jun": "",
    "Aug": "",
    "Mar": "",
    "Feb": "",
    "Jan": "",
    "Jul": ""
  },
  {
    "Sep": "",
    "Total": "2",
    "Dec": "",
    "May": "",
    "Apr": "",
    "Nov": "",
    "City": "Saint James",
    "Oct": "",
    "Jun": "1",
    "Aug": "",
    "Mar": "",
    "Feb": "1",
    "Jan": "",
    "Jul": ""
  },
  {
    "Sep": "3",
    "Total": "14",
    "Dec": "",
    "May": "2",
    "Apr": "",
    "Nov": "3",
    "City": "Saint Paul",
    "Oct": "2",
    "Jun": "2",
    "Aug": "",
    "Mar": "",
    "Feb": "",
    "Jan": "",
    "Jul": "2"
  },
  {
    "Sep": "",
    "Total": "1",
    "Dec": "",
    "May": "",
    "Apr": "",
    "Nov": "",
    "City": "Saint Peter",
    "Oct": "",
    "Jun": "",
    "Aug": "",
    "Mar": "",
    "Feb": "",
    "Jan": "",
    "Jul": "1"
  },
  {
    "Sep": "1",
    "Total": "1",
    "Dec": "",
    "May": "",
    "Apr": "",
    "Nov": "",
    "City": "Sandstone",
    "Oct": "",
    "Jun": "",
    "Aug": "",
    "Mar": "",
    "Feb": "",
    "Jan": "",
    "Jul": ""
  },
  {
    "Sep": "",
    "Total": "6",
    "Dec": "",
    "May": "2",
    "Apr": "",
    "Nov": "1",
    "City": "Sartell",
    "Oct": "1",
    "Jun": "1",
    "Aug": "1",
    "Mar": "",
    "Feb": "",
    "Jan": "",
    "Jul": ""
  },
  {
    "Sep": "",
    "Total": "1",
    "Dec": "",
    "May": "",
    "Apr": "",
    "Nov": "",
    "City": "Sauk Centre",
    "Oct": "1",
    "Jun": "",
    "Aug": "",
    "Mar": "",
    "Feb": "",
    "Jan": "",
    "Jul": ""
  },
  {
    "Sep": "1",
    "Total": "5",
    "Dec": "",
    "May": "",
    "Apr": "",
    "Nov": "",
    "City": "Sauk Rapids",
    "Oct": "",
    "Jun": "1",
    "Aug": "",
    "Mar": "1",
    "Feb": "",
    "Jan": "1",
    "Jul": "1"
  },
  {
    "Sep": "2",
    "Total": "8",
    "Dec": "",
    "May": "1",
    "Apr": "",
    "Nov": "",
    "City": "Savage",
    "Oct": "1",
    "Jun": "2",
    "Aug": "1",
    "Mar": "",
    "Feb": "",
    "Jan": "1",
    "Jul": ""
  },
  {
    "Sep": "1",
    "Total": "1",
    "Dec": "",
    "May": "",
    "Apr": "",
    "Nov": "",
    "City": "Scandia",
    "Oct": "",
    "Jun": "",
    "Aug": "",
    "Mar": "",
    "Feb": "",
    "Jan": "",
    "Jul": ""
  },
  {
    "Sep": "2",
    "Total": "13",
    "Dec": "1",
    "May": "1",
    "Apr": "",
    "Nov": "",
    "City": "Shakopee",
    "Oct": "3",
    "Jun": "3",
    "Aug": "3",
    "Mar": "",
    "Feb": "",
    "Jan": "",
    "Jul": ""
  },
  {
    "Sep": "",
    "Total": "1",
    "Dec": "",
    "May": "1",
    "Apr": "",
    "Nov": "",
    "City": "Shoreview",
    "Oct": "",
    "Jun": "",
    "Aug": "",
    "Mar": "",
    "Feb": "",
    "Jan": "",
    "Jul": ""
  },
  {
    "Sep": "",
    "Total": "1",
    "Dec": "",
    "May": "",
    "Apr": "",
    "Nov": "",
    "City": "Silver Bay",
    "Oct": "",
    "Jun": "",
    "Aug": "",
    "Mar": "",
    "Feb": "",
    "Jan": "",
    "Jul": "1"
  },
  {
    "Sep": "",
    "Total": "4",
    "Dec": "",
    "May": "1",
    "Apr": "1",
    "Nov": "",
    "City": "Sleepy Eye",
    "Oct": "",
    "Jun": "1",
    "Aug": "1",
    "Mar": "",
    "Feb": "",
    "Jan": "",
    "Jul": ""
  },
  {
    "Sep": "",
    "Total": "1",
    "Dec": "",
    "May": "",
    "Apr": "",
    "Nov": "",
    "City": "South Saint Paul",
    "Oct": "",
    "Jun": "1",
    "Aug": "",
    "Mar": "",
    "Feb": "",
    "Jan": "",
    "Jul": ""
  },
  {
    "Sep": "",
    "Total": "1",
    "Dec": "",
    "May": "1",
    "Apr": "",
    "Nov": "",
    "City": "South St. Paul",
    "Oct": "",
    "Jun": "",
    "Aug": "",
    "Mar": "",
    "Feb": "",
    "Jan": "",
    "Jul": ""
  },
  {
    "Sep": "",
    "Total": "4",
    "Dec": "",
    "May": "",
    "Apr": "",
    "Nov": "",
    "City": "Spicer",
    "Oct": "",
    "Jun": "",
    "Aug": "2",
    "Mar": "",
    "Feb": "",
    "Jan": "1",
    "Jul": "1"
  },
  {
    "Sep": "",
    "Total": "1",
    "Dec": "",
    "May": "",
    "Apr": "",
    "Nov": "",
    "City": "Spring Grove",
    "Oct": "1",
    "Jun": "",
    "Aug": "",
    "Mar": "",
    "Feb": "",
    "Jan": "",
    "Jul": ""
  },
  {
    "Sep": "",
    "Total": "1",
    "Dec": "",
    "May": "1",
    "Apr": "",
    "Nov": "",
    "City": "Spring Valley",
    "Oct": "",
    "Jun": "",
    "Aug": "",
    "Mar": "",
    "Feb": "",
    "Jan": "",
    "Jul": ""
  },
  {
    "Sep": "",
    "Total": "2",
    "Dec": "",
    "May": "",
    "Apr": "2",
    "Nov": "",
    "City": "St Cloud",
    "Oct": "",
    "Jun": "",
    "Aug": "",
    "Mar": "",
    "Feb": "",
    "Jan": "",
    "Jul": ""
  },
  {
    "Sep": "2",
    "Total": "10",
    "Dec": "",
    "May": "1",
    "Apr": "",
    "Nov": "",
    "City": "St Paul",
    "Oct": "3",
    "Jun": "2",
    "Aug": "",
    "Mar": "",
    "Feb": "",
    "Jan": "1",
    "Jul": "1"
  },
  {
    "Sep": "",
    "Total": "1",
    "Dec": "",
    "May": "",
    "Apr": "",
    "Nov": "",
    "City": "St. Augusta",
    "Oct": "",
    "Jun": "1",
    "Aug": "",
    "Mar": "",
    "Feb": "",
    "Jan": "",
    "Jul": ""
  },
  {
    "Sep": "",
    "Total": "1",
    "Dec": "",
    "May": "",
    "Apr": "",
    "Nov": "",
    "City": "St. Bonifacius",
    "Oct": "",
    "Jun": "",
    "Aug": "",
    "Mar": "",
    "Feb": "",
    "Jan": "",
    "Jul": "1"
  },
  {
    "Sep": "",
    "Total": "1",
    "Dec": "",
    "May": "",
    "Apr": "",
    "Nov": "",
    "City": "St. Charles",
    "Oct": "",
    "Jun": "",
    "Aug": "",
    "Mar": "",
    "Feb": "",
    "Jan": "",
    "Jul": "1"
  },
  {
    "Sep": "",
    "Total": "1",
    "Dec": "",
    "May": "",
    "Apr": "",
    "Nov": "",
    "City": "St. Clair",
    "Oct": "",
    "Jun": "1",
    "Aug": "",
    "Mar": "",
    "Feb": "",
    "Jan": "",
    "Jul": ""
  },
  {
    "Sep": "3",
    "Total": "9",
    "Dec": "",
    "May": "1",
    "Apr": "",
    "Nov": "",
    "City": "St. Cloud",
    "Oct": "2",
    "Jun": "1",
    "Aug": "1",
    "Mar": "1",
    "Feb": "",
    "Jan": "",
    "Jul": ""
  },
  {
    "Sep": "",
    "Total": "1",
    "Dec": "",
    "May": "",
    "Apr": "",
    "Nov": "",
    "City": "St. Francis",
    "Oct": "",
    "Jun": "1",
    "Aug": "",
    "Mar": "",
    "Feb": "",
    "Jan": "",
    "Jul": ""
  },
  {
    "Sep": "2",
    "Total": "4",
    "Dec": "1",
    "May": "1",
    "Apr": "",
    "Nov": "",
    "City": "St. Joseph",
    "Oct": "",
    "Jun": "",
    "Aug": "",
    "Mar": "",
    "Feb": "",
    "Jan": "",
    "Jul": ""
  },
  {
    "Sep": "3",
    "Total": "9",
    "Dec": "1",
    "May": "",
    "Apr": "1",
    "Nov": "",
    "City": "St. Louis Park",
    "Oct": "1",
    "Jun": "",
    "Aug": "1",
    "Mar": "",
    "Feb": "",
    "Jan": "1",
    "Jul": "1"
  },
  {
    "Sep": "",
    "Total": "3",
    "Dec": "",
    "May": "",
    "Apr": "",
    "Nov": "",
    "City": "St. Michael",
    "Oct": "",
    "Jun": "1",
    "Aug": "2",
    "Mar": "",
    "Feb": "",
    "Jan": "",
    "Jul": ""
  },
  {
    "Sep": "8",
    "Total": "62",
    "Dec": "5",
    "May": "10",
    "Apr": "2",
    "Nov": "4",
    "City": "St. Paul",
    "Oct": "6",
    "Jun": "3",
    "Aug": "12",
    "Mar": "4",
    "Feb": "1",
    "Jan": "",
    "Jul": "7"
  },
  {
    "Sep": "",
    "Total": "4",
    "Dec": "",
    "May": "1",
    "Apr": "1",
    "Nov": "",
    "City": "St. Peter",
    "Oct": "1",
    "Jun": "",
    "Aug": "",
    "Mar": "1",
    "Feb": "",
    "Jan": "",
    "Jul": ""
  },
  {
    "Sep": "",
    "Total": "1",
    "Dec": "",
    "May": "",
    "Apr": "",
    "Nov": "",
    "City": "Staples",
    "Oct": "",
    "Jun": "",
    "Aug": "1",
    "Mar": "",
    "Feb": "",
    "Jan": "",
    "Jul": ""
  },
  {
    "Sep": "",
    "Total": "1",
    "Dec": "",
    "May": "",
    "Apr": "",
    "Nov": "",
    "City": "Starbuck",
    "Oct": "",
    "Jun": "",
    "Aug": "",
    "Mar": "",
    "Feb": "",
    "Jan": "",
    "Jul": "1"
  },
  {
    "Sep": "",
    "Total": "1",
    "Dec": "",
    "May": "",
    "Apr": "",
    "Nov": "",
    "City": "Stewartville",
    "Oct": "",
    "Jun": "",
    "Aug": "",
    "Mar": "",
    "Feb": "",
    "Jan": "",
    "Jul": "1"
  },
  {
    "Sep": "3",
    "Total": "6",
    "Dec": "",
    "May": "2",
    "Apr": "",
    "Nov": "",
    "City": "Stillwater",
    "Oct": "",
    "Jun": "1",
    "Aug": "",
    "Mar": "",
    "Feb": "",
    "Jan": "",
    "Jul": ""
  },
  {
    "Sep": "1",
    "Total": "1",
    "Dec": "",
    "May": "",
    "Apr": "",
    "Nov": "",
    "City": "Taylors Falls",
    "Oct": "",
    "Jun": "",
    "Aug": "",
    "Mar": "",
    "Feb": "",
    "Jan": "",
    "Jul": ""
  },
  {
    "Sep": "",
    "Total": "2",
    "Dec": "",
    "May": "",
    "Apr": "2",
    "Nov": "",
    "City": "Theilman",
    "Oct": "",
    "Jun": "",
    "Aug": "",
    "Mar": "",
    "Feb": "",
    "Jan": "",
    "Jul": ""
  },
  {
    "Sep": "",
    "Total": "3",
    "Dec": "",
    "May": "2",
    "Apr": "",
    "Nov": "",
    "City": "Thief River Falls",
    "Oct": "",
    "Jun": "1",
    "Aug": "",
    "Mar": "",
    "Feb": "",
    "Jan": "",
    "Jul": ""
  },
  {
    "Sep": "",
    "Total": "1",
    "Dec": "",
    "May": "",
    "Apr": "",
    "Nov": "",
    "City": "Tofte",
    "Oct": "",
    "Jun": "",
    "Aug": "",
    "Mar": "",
    "Feb": "",
    "Jan": "",
    "Jul": "1"
  },
  {
    "Sep": "",
    "Total": "1",
    "Dec": "",
    "May": "",
    "Apr": "",
    "Nov": "",
    "City": "Tower",
    "Oct": "",
    "Jun": "",
    "Aug": "",
    "Mar": "",
    "Feb": "",
    "Jan": "",
    "Jul": "1"
  },
  {
    "Sep": "",
    "Total": "1",
    "Dec": "",
    "May": "",
    "Apr": "",
    "Nov": "",
    "City": "Twig",
    "Oct": "",
    "Jun": "",
    "Aug": "1",
    "Mar": "",
    "Feb": "",
    "Jan": "",
    "Jul": ""
  },
  {
    "Sep": "",
    "Total": "2",
    "Dec": "",
    "May": "",
    "Apr": "",
    "Nov": "",
    "City": "Two Harbors",
    "Oct": "",
    "Jun": "",
    "Aug": "",
    "Mar": "",
    "Feb": "1",
    "Jan": "",
    "Jul": "1"
  },
  {
    "Sep": "",
    "Total": "1",
    "Dec": "",
    "May": "",
    "Apr": "",
    "Nov": "",
    "City": "Tyler",
    "Oct": "",
    "Jun": "1",
    "Aug": "",
    "Mar": "",
    "Feb": "",
    "Jan": "",
    "Jul": ""
  },
  {
    "Sep": "",
    "Total": "1",
    "Dec": "",
    "May": "",
    "Apr": "",
    "Nov": "",
    "City": "Ulen",
    "Oct": "",
    "Jun": "",
    "Aug": "1",
    "Mar": "",
    "Feb": "",
    "Jan": "",
    "Jul": ""
  },
  {
    "Sep": "",
    "Total": "1",
    "Dec": "",
    "May": "",
    "Apr": "",
    "Nov": "",
    "City": "Vadnais Heights",
    "Oct": "",
    "Jun": "",
    "Aug": "",
    "Mar": "",
    "Feb": "1",
    "Jan": "",
    "Jul": ""
  },
  {
    "Sep": "",
    "Total": "2",
    "Dec": "",
    "May": "",
    "Apr": "1",
    "Nov": "",
    "City": "Vergas",
    "Oct": "1",
    "Jun": "",
    "Aug": "",
    "Mar": "",
    "Feb": "",
    "Jan": "",
    "Jul": ""
  },
  {
    "Sep": "",
    "Total": "1",
    "Dec": "",
    "May": "",
    "Apr": "",
    "Nov": "",
    "City": "Vining",
    "Oct": "",
    "Jun": "",
    "Aug": "1",
    "Mar": "",
    "Feb": "",
    "Jan": "",
    "Jul": ""
  },
  {
    "Sep": "",
    "Total": "3",
    "Dec": "",
    "May": "",
    "Apr": "",
    "Nov": "",
    "City": "Virginia",
    "Oct": "1",
    "Jun": "1",
    "Aug": "",
    "Mar": "",
    "Feb": "",
    "Jan": "",
    "Jul": "1"
  },
  {
    "Sep": "",
    "Total": "2",
    "Dec": "",
    "May": "",
    "Apr": "",
    "Nov": "",
    "City": "Wabasha",
    "Oct": "",
    "Jun": "1",
    "Aug": "",
    "Mar": "",
    "Feb": "",
    "Jan": "",
    "Jul": "1"
  },
  {
    "Sep": "1",
    "Total": "7",
    "Dec": "",
    "May": "",
    "Apr": "2",
    "Nov": "",
    "City": "Waconia",
    "Oct": "",
    "Jun": "2",
    "Aug": "2",
    "Mar": "",
    "Feb": "",
    "Jan": "",
    "Jul": ""
  },
  {
    "Sep": "",
    "Total": "2",
    "Dec": "",
    "May": "",
    "Apr": "",
    "Nov": "",
    "City": "Wadena",
    "Oct": "1",
    "Jun": "",
    "Aug": "1",
    "Mar": "",
    "Feb": "",
    "Jan": "",
    "Jul": ""
  },
  {
    "Sep": "",
    "Total": "1",
    "Dec": "",
    "May": "",
    "Apr": "",
    "Nov": "",
    "City": "Waite Park",
    "Oct": "",
    "Jun": "1",
    "Aug": "",
    "Mar": "",
    "Feb": "",
    "Jan": "",
    "Jul": ""
  },
  {
    "Sep": "1",
    "Total": "5",
    "Dec": "",
    "May": "",
    "Apr": "",
    "Nov": "",
    "City": "Walker",
    "Oct": "1",
    "Jun": "",
    "Aug": "1",
    "Mar": "",
    "Feb": "",
    "Jan": "",
    "Jul": "2"
  },
  {
    "Sep": "",
    "Total": "1",
    "Dec": "",
    "May": "",
    "Apr": "",
    "Nov": "",
    "City": "Warroad",
    "Oct": "",
    "Jun": "",
    "Aug": "1",
    "Mar": "",
    "Feb": "",
    "Jan": "",
    "Jul": ""
  },
  {
    "Sep": "",
    "Total": "1",
    "Dec": "",
    "May": "",
    "Apr": "",
    "Nov": "",
    "City": "Waseca",
    "Oct": "",
    "Jun": "",
    "Aug": "1",
    "Mar": "",
    "Feb": "",
    "Jan": "",
    "Jul": ""
  },
  {
    "Sep": "",
    "Total": "2",
    "Dec": "",
    "May": "",
    "Apr": "",
    "Nov": "",
    "City": "Watertown",
    "Oct": "1",
    "Jun": "",
    "Aug": "",
    "Mar": "",
    "Feb": "",
    "Jan": "",
    "Jul": "1"
  },
  {
    "Sep": "",
    "Total": "1",
    "Dec": "",
    "May": "",
    "Apr": "",
    "Nov": "",
    "City": "Waterville",
    "Oct": "",
    "Jun": "1",
    "Aug": "",
    "Mar": "",
    "Feb": "",
    "Jan": "",
    "Jul": ""
  },
  {
    "Sep": "",
    "Total": "3",
    "Dec": "",
    "May": "1",
    "Apr": "2",
    "Nov": "",
    "City": "Wayzata",
    "Oct": "",
    "Jun": "",
    "Aug": "",
    "Mar": "",
    "Feb": "",
    "Jan": "",
    "Jul": ""
  },
  {
    "Sep": "",
    "Total": "1",
    "Dec": "",
    "May": "",
    "Apr": "",
    "Nov": "",
    "City": "Welch",
    "Oct": "",
    "Jun": "",
    "Aug": "1",
    "Mar": "",
    "Feb": "",
    "Jan": "",
    "Jul": ""
  },
  {
    "Sep": "",
    "Total": "1",
    "Dec": "",
    "May": "",
    "Apr": "",
    "Nov": "",
    "City": "Wheaton",
    "Oct": "",
    "Jun": "",
    "Aug": "1",
    "Mar": "",
    "Feb": "",
    "Jan": "",
    "Jul": ""
  },
  {
    "Sep": "2",
    "Total": "21",
    "Dec": "1",
    "May": "2",
    "Apr": "3",
    "Nov": "2",
    "City": "White Bear Lake",
    "Oct": "2",
    "Jun": "3",
    "Aug": "2",
    "Mar": "1",
    "Feb": "",
    "Jan": "2",
    "Jul": "1"
  },
  {
    "Sep": "",
    "Total": "8",
    "Dec": "",
    "May": "1",
    "Apr": "",
    "Nov": "1",
    "City": "Willmar",
    "Oct": "2",
    "Jun": "1",
    "Aug": "2",
    "Mar": "1",
    "Feb": "",
    "Jan": "",
    "Jul": ""
  },
  {
    "Sep": "2",
    "Total": "15",
    "Dec": "",
    "May": "2",
    "Apr": "1",
    "Nov": "1",
    "City": "Winona",
    "Oct": "2",
    "Jun": "4",
    "Aug": "1",
    "Mar": "",
    "Feb": "1",
    "Jan": "",
    "Jul": "1"
  },
  {
    "Sep": "",
    "Total": "1",
    "Dec": "",
    "May": "",
    "Apr": "",
    "Nov": "",
    "City": "Winthrop",
    "Oct": "",
    "Jun": "",
    "Aug": "",
    "Mar": "",
    "Feb": "",
    "Jan": "",
    "Jul": "1"
  },
  {
    "Sep": "",
    "Total": "1",
    "Dec": "",
    "May": "",
    "Apr": "",
    "Nov": "",
    "City": "Wirt",
    "Oct": "",
    "Jun": "1",
    "Aug": "",
    "Mar": "",
    "Feb": "",
    "Jan": "",
    "Jul": ""
  },
  {
    "Sep": "",
    "Total": "10",
    "Dec": "",
    "May": "1",
    "Apr": "2",
    "Nov": "1",
    "City": "Woodbury",
    "Oct": "1",
    "Jun": "",
    "Aug": "3",
    "Mar": "",
    "Feb": "",
    "Jan": "2",
    "Jul": ""
  },
  {
    "Sep": "1",
    "Total": "2",
    "Dec": "",
    "May": "",
    "Apr": "",
    "Nov": "",
    "City": "Worthington",
    "Oct": "",
    "Jun": "1",
    "Aug": "",
    "Mar": "",
    "Feb": "",
    "Jan": "",
    "Jul": ""
  },
  {
    "Sep": "",
    "Total": "1",
    "Dec": "",
    "May": "",
    "Apr": "",
    "Nov": "",
    "City": "Wrenshall",
    "Oct": "",
    "Jun": "",
    "Aug": "1",
    "Mar": "",
    "Feb": "",
    "Jan": "",
    "Jul": ""
  },
  {
    "Sep": "",
    "Total": "2",
    "Dec": "",
    "May": "",
    "Apr": "",
    "Nov": "",
    "City": "Wyoming",
    "Oct": "",
    "Jun": "",
    "Aug": "2",
    "Mar": "",
    "Feb": "",
    "Jan": "",
    "Jul": ""
  },
  {
    "Sep": "",
    "Total": "3",
    "Dec": "",
    "May": "",
    "Apr": "1",
    "Nov": "",
    "City": "Zimmerman",
    "Oct": "1",
    "Jun": "1",
    "Aug": "",
    "Mar": "",
    "Feb": "",
    "Jan": "",
    "Jul": ""
  },
  {
    "Sep": "",
    "Total": "2",
    "Dec": "",
    "May": "",
    "Apr": "",
    "Nov": "",
    "City": "Zumbro Falls",
    "Oct": "1",
    "Jun": "",
    "Aug": "1",
    "Mar": "",
    "Feb": "",
    "Jan": "",
    "Jul": ""
  },
  {
    "Sep": "",
    "Total": "1",
    "Dec": "",
    "May": "",
    "Apr": "",
    "Nov": "",
    "City": "Zumbrota",
    "Oct": "",
    "Jun": "1",
    "Aug": "",
    "Mar": "",
    "Feb": "",
    "Jan": "",
    "Jul": ""
  },
  {
    "Sep": "187",
    "Total": "1221",
    "Dec": "25",
    "May": "162",
    "Apr": "77",
    "Nov": "39",
    "City": "Total",
    "Oct": "120",
    "Jun": "183",
    "Aug": "185",
    "Mar": "32",
    "Feb": "26",
    "Jan": "32",
    "Jul": "153"
  }
]